Workbook

Sheet README
A1: Example ledger: every TRANSFER case
A3: Anonymised example that goes with the blog post on how I keep my books. All names, accounts and amounts are made up.
A4: ENTRIES holds the rows. Filter column case to see one example; the note column says what each row does.
A5: CHECKS tests the rules: TRANSFER sums to zero overall and per id, helper sources return to zero, euro amounts match fx_amount / rate.
A6: SUMMARY shows income, spending and net worth, and proves that transfers change none of them.
A7: CODES holds the lists behind the dropdowns on ENTRIES.
A8: WHEREABOUTS lists where I was: one row per arrival, with Work TRUE for a stay with a job. The dashboard uses it for the days in Asia, the groceries per stay and the Work tab.
A9: Legend
A10: Blue text | B10: Values you type (the inputs). Edit these.
A11: Black text | B11: Formulas. Leave these alone.
A12: Grey rows | B12: TRANSFER rows on ENTRIES.
A13: Signs | B13: amount is in euros, seen from the source: + is money in, - is money out.
A15: case | B15: family | C15: what happens | D15: how it is booked | E15: rows | F15: TRANSFER sum | G15: effect on income | H15: effect on spending
A16: O1 | B16: Setup | C16: Opening balances | D16: The balance of each source on the first day of the file. Not income, not a transfer. | E16: =COUNTIF(ENTRIES!$A$2:$A$2000,A16) -> 5 | F16: =ROUND(SUMIFS(ENTRIES!$E$2:$E$2000,ENTRIES!$A$2:$A$2000,A16,ENTRIES!$G$2:$G$2000,"TRANSFER"),2) -> 0 | G16: =SUMIFS(ENTRIES!$E$2:$E$2000,ENTRIES!$A$2:$A$2000,A16,ENTRIES!$G$2:$G$2000,"IN") -> 0 | H16: =SUMPRODUCT((ENTRIES!$A$2:$A$2000=A16)*(LEFT(ENTRIES!$G$2:$G$2000,3)="OUT"),ENTRIES!$E$2:$E$2000) -> 0
A17: B0 | B17: Background | C17: Ordinary rows | D17: Normal income and spending, so the example balances look like a real season. | E17: =COUNTIF(ENTRIES!$A$2:$A$2000,A17) -> 641 | F17: =ROUND(SUMIFS(ENTRIES!$E$2:$E$2000,ENTRIES!$A$2:$A$2000,A17,ENTRIES!$G$2:$G$2000,"TRANSFER"),2) -> 0 | G17: =SUMIFS(ENTRIES!$E$2:$E$2000,ENTRIES!$A$2:$A$2000,A17,ENTRIES!$G$2:$G$2000,"IN") -> 4957.3 | H17: =SUMPRODUCT((ENTRIES!$A$2:$A$2000=A17)*(LEFT(ENTRIES!$G$2:$G$2000,3)="OUT"),ENTRIES!$E$2:$E$2000) -> -3788.38
A18: T01 | B18: A. Between my own sources | C18: Saving: current account to savings | D18: The classic pair. Two legs, same id, opposite amounts. | E18: =COUNTIF(ENTRIES!$A$2:$A$2000,A18) -> 4 | F18: =ROUND(SUMIFS(ENTRIES!$E$2:$E$2000,ENTRIES!$A$2:$A$2000,A18,ENTRIES!$G$2:$G$2000,"TRANSFER"),2) -> 0 | G18: =SUMIFS(ENTRIES!$E$2:$E$2000,ENTRIES!$A$2:$A$2000,A18,ENTRIES!$G$2:$G$2000,"IN") -> 0 | H18: =SUMPRODUCT((ENTRIES!$A$2:$A$2000=A18)*(LEFT(ENTRIES!$G$2:$G$2000,3)="OUT"),ENTRIES!$E$2:$E$2000) -> 0
A19: T02 | B19: A. Between my own sources | C19: Cash from a home ATM | D19: Cash is a source like any other, so a withdrawal is a transfer, not spending. | E19: =COUNTIF(ENTRIES!$A$2:$A$2000,A19) -> 2 | F19: =ROUND(SUMIFS(ENTRIES!$E$2:$E$2000,ENTRIES!$A$2:$A$2000,A19,ENTRIES!$G$2:$G$2000,"TRANSFER"),2) -> 0 | G19: =SUMIFS(ENTRIES!$E$2:$E$2000,ENTRIES!$A$2:$A$2000,A19,ENTRIES!$G$2:$G$2000,"IN") -> 0 | H19: =SUMPRODUCT((ENTRIES!$A$2:$A$2000=A19)*(LEFT(ENTRIES!$G$2:$G$2000,3)="OUT"),ENTRIES!$E$2:$E$2000) -> 0
A20: T03 | B20: A. Between my own sources | C20: ATM abroad, with a local ATM fee | D20: Book the transfer at the euro amount the bank charged and the gross local amount; the fee is a negative expense row inside the cash wallet. | E20: =COUNTIF(ENTRIES!$A$2:$A$2000,A20) -> 3 | F20: =ROUND(SUMIFS(ENTRIES!$E$2:$E$2000,ENTRIES!$A$2:$A$2000,A20,ENTRIES!$G$2:$G$2000,"TRANSFER"),2) -> 0 | G20: =SUMIFS(ENTRIES!$E$2:$E$2000,ENTRIES!$A$2:$A$2000,A20,ENTRIES!$G$2:$G$2000,"IN") -> 0 | H20: =SUMPRODUCT((ENTRIES!$A$2:$A$2000=A20)*(LEFT(ENTRIES!$G$2:$G$2000,3)="OUT"),ENTRIES!$E$2:$E$2000) -> -6.77
A21: T04 | B21: A. Between my own sources | C21: Exchange inside a multi-currency app | D21: One source per currency pocket. The exchange is a transfer between two of them. | E21: =COUNTIF(ENTRIES!$A$2:$A$2000,A21) -> 4 | F21: =ROUND(SUMIFS(ENTRIES!$E$2:$E$2000,ENTRIES!$A$2:$A$2000,A21,ENTRIES!$G$2:$G$2000,"TRANSFER"),2) -> 0 | G21: =SUMIFS(ENTRIES!$E$2:$E$2000,ENTRIES!$A$2:$A$2000,A21,ENTRIES!$G$2:$G$2000,"IN") -> 0 | H21: =SUMPRODUCT((ENTRIES!$A$2:$A$2000=A21)*(LEFT(ENTRIES!$G$2:$G$2000,3)="OUT"),ENTRIES!$E$2:$E$2000) -> 0
A22: T05 | B22: A. Between my own sources | C22: Credit card: purchase, then monthly settlement | D22: The purchase is the expense, on the card. The settlement from the bank is only a transfer. | E22: =COUNTIF(ENTRIES!$A$2:$A$2000,A22) -> 3 | F22: =ROUND(SUMIFS(ENTRIES!$E$2:$E$2000,ENTRIES!$A$2:$A$2000,A22,ENTRIES!$G$2:$G$2000,"TRANSFER"),2) -> 0 | G22: =SUMIFS(ENTRIES!$E$2:$E$2000,ENTRIES!$A$2:$A$2000,A22,ENTRIES!$G$2:$G$2000,"IN") -> 0 | H22: =SUMPRODUCT((ENTRIES!$A$2:$A$2000=A22)*(LEFT(ENTRIES!$G$2:$G$2000,3)="OUT"),ENTRIES!$E$2:$E$2000) -> -612.4
A23: T06 | B23: A. Between my own sources | C23: Top up an online bank, pay a fee, pay rent | D23: Top-up is a transfer; the service fee is an expense; the rent is an expense. Three rows on the online bank, one on the bank. | E23: =COUNTIF(ENTRIES!$A$2:$A$2000,A23) -> 4 | F23: =ROUND(SUMIFS(ENTRIES!$E$2:$E$2000,ENTRIES!$A$2:$A$2000,A23,ENTRIES!$G$2:$G$2000,"TRANSFER"),2) -> 0 | G23: =SUMIFS(ENTRIES!$E$2:$E$2000,ENTRIES!$A$2:$A$2000,A23,ENTRIES!$G$2:$G$2000,"IN") -> 0 | H23: =SUMPRODUCT((ENTRIES!$A$2:$A$2000=A23)*(LEFT(ENTRIES!$G$2:$G$2000,3)="OUT"),ENTRIES!$E$2:$E$2000) -> -126.45
A24: T07 | B24: A. Between my own sources | C24: A transfer that arrives short | D24: The bank shows one line of -150. I split it: -149.50 transfer and -0.50 fee, same id. The legs stay equal. | E24: =COUNTIF(ENTRIES!$A$2:$A$2000,A24) -> 3 | F24: =ROUND(SUMIFS(ENTRIES!$E$2:$E$2000,ENTRIES!$A$2:$A$2000,A24,ENTRIES!$G$2:$G$2000,"TRANSFER"),2) -> 0 | G24: =SUMIFS(ENTRIES!$E$2:$E$2000,ENTRIES!$A$2:$A$2000,A24,ENTRIES!$G$2:$G$2000,"IN") -> 0 | H24: =SUMPRODUCT((ENTRIES!$A$2:$A$2000=A24)*(LEFT(ENTRIES!$G$2:$G$2000,3)="OUT"),ENTRIES!$E$2:$E$2000) -> -0.5
A25: T08 | B25: A. Between my own sources | C25: Cash-to-cash exchange at an airport | D25: Leftover dollars swapped for dirhams during a layover. Both legs in euros, each with its own local amount and rate. | E25: =COUNTIF(ENTRIES!$A$2:$A$2000,A25) -> 2 | F25: =ROUND(SUMIFS(ENTRIES!$E$2:$E$2000,ENTRIES!$A$2:$A$2000,A25,ENTRIES!$G$2:$G$2000,"TRANSFER"),2) -> 0 | G25: =SUMIFS(ENTRIES!$E$2:$E$2000,ENTRIES!$A$2:$A$2000,A25,ENTRIES!$G$2:$G$2000,"IN") -> 0 | H25: =SUMPRODUCT((ENTRIES!$A$2:$A$2000=A25)*(LEFT(ENTRIES!$G$2:$G$2000,3)="OUT"),ENTRIES!$E$2:$E$2000) -> 0
A26: T09 | B26: A. Between my own sources | C26: A transfer that crosses a month boundary | D26: Each leg gets the date it happened on its own source. January shows -500, February +500, the pair is zero. | E26: =COUNTIF(ENTRIES!$A$2:$A$2000,A26) -> 2 | F26: =ROUND(SUMIFS(ENTRIES!$E$2:$E$2000,ENTRIES!$A$2:$A$2000,A26,ENTRIES!$G$2:$G$2000,"TRANSFER"),2) -> 0 | G26: =SUMIFS(ENTRIES!$E$2:$E$2000,ENTRIES!$A$2:$A$2000,A26,ENTRIES!$G$2:$G$2000,"IN") -> 0 | H26: =SUMPRODUCT((ENTRIES!$A$2:$A$2000=A26)*(LEFT(ENTRIES!$G$2:$G$2000,3)="OUT"),ENTRIES!$E$2:$E$2000) -> 0
A27: T10 | B27: A. Between my own sources | C27: Rate adjusted so both legs are equal | D27: The app credited 3,690 THB for 100.00 EUR. I set the rate on the THB leg by hand to 3,690 / 100 = 36.90, so both legs are exactly 100.00. | E27: =COUNTIF(ENTRIES!$A$2:$A$2000,A27) -> 2 | F27: =ROUND(SUMIFS(ENTRIES!$E$2:$E$2000,ENTRIES!$A$2:$A$2000,A27,ENTRIES!$G$2:$G$2000,"TRANSFER"),2) -> 0 | G27: =SUMIFS(ENTRIES!$E$2:$E$2000,ENTRIES!$A$2:$A$2000,A27,ENTRIES!$G$2:$G$2000,"IN") -> 0 | H27: =SUMPRODUCT((ENTRIES!$A$2:$A$2000=A27)*(LEFT(ENTRIES!$G$2:$G$2000,3)="OUT"),ENTRIES!$E$2:$E$2000) -> 0
... A50: Z4 | B50: E. Housekeeping rows | C50: Year-end checkpoint | D50: On 31 December a zero row per source with the balance in the description. Next year I can see at once whether old rows were changed. | E50: =COUNTIF(ENTRIES!$A$2:$A$2000,A50) -> 3 | F50: =ROUND(SUMIFS(ENTRIES!$E$2:$E$2000,ENTRIES!$A$2:$A$2000,A50,ENTRIES!$G$2:$G$2000,"TRANSFER"),2) -> 0 | G50: =SUMIFS(ENTRIES!$E$2:$E$2000,ENTRIES!$A$2:$A$2000,A50,ENTRIES!$G$2:$G$2000,"IN") -> 0 | H50: =SUMPRODUCT((ENTRIES!$A$2:$A$2000=A50)*(LEFT(ENTRIES!$G$2:$G$2000,3)="OUT"),ENTRIES!$E$2:$E$2000) -> 0
A52: Effect on spending uses the sign of amount: negative = this case adds to spending (money out), positive = it reduces spending. Transfers add nothing.

Sheet ENTRIES
A1: case | B1: id | C1: source | D1: date | E1: amount | F1: description | G1: type | H1: group | I1: category | J1: daily_code | K1: fx_amount | L1: currency | M1: rate | N1: fx_check | O1: month | P1: note
A2: O1 | B2: 100 | C2: BANK_CURRENT | D2: 45961 | E2: 6600 | F2: opening balance | G2: OPENING_BALANCE | H2: OPENING_BALANCE | I2: opening_balance | N2: =IF(OR(K2="",M2=""),"",IF(C2="STATS_ONLY","stats",IF(ROUND(K2/M2,2)=E2,"OK","CHECK"))) | O2: =TEXT(D2,"yyyy-mm") -> 2025-10 | P2: first row of every source
A3: O1 | B3: 100 | C3: BANK_SAVINGS | D3: 45961 | E3: 8000 | F3: opening balance | G3: OPENING_BALANCE | H3: OPENING_BALANCE | I3: opening_balance | N3: =IF(OR(K3="",M3=""),"",IF(C3="STATS_ONLY","stats",IF(ROUND(K3/M3,2)=E3,"OK","CHECK"))) | O3: =TEXT(D3,"yyyy-mm") -> 2025-10 | P3: first row of every source
A4: O1 | B4: 100 | C4: BANK_PENSION | D4: 45961 | E4: 2400 | F4: opening balance | G4: OPENING_BALANCE | H4: OPENING_BALANCE | I4: opening_balance | N4: =IF(OR(K4="",M4=""),"",IF(C4="STATS_ONLY","stats",IF(ROUND(K4/M4,2)=E4,"OK","CHECK"))) | O4: =TEXT(D4,"yyyy-mm") -> 2025-10 | P4: first row of every source
A5: O1 | B5: 100 | C5: CASH_EUR | D5: 45961 | E5: 150 | F5: opening balance | G5: OPENING_BALANCE | H5: OPENING_BALANCE | I5: opening_balance | N5: =IF(OR(K5="",M5=""),"",IF(C5="STATS_ONLY","stats",IF(ROUND(K5/M5,2)=E5,"OK","CHECK"))) | O5: =TEXT(D5,"yyyy-mm") -> 2025-10 | P5: first row of every source
A6: O1 | B6: 100 | C6: CASH_USD | D6: 45961 | E6: 51.24 | F6: opening balance | G6: OPENING_BALANCE | H6: OPENING_BALANCE | I6: opening_balance | K6: 60 | L6: USD | M6: 1.1709602 | N6: =IF(OR(K6="",M6=""),"",IF(C6="STATS_ONLY","stats",IF(ROUND(K6/M6,2)=E6,"OK","CHECK"))) -> OK | O6: =TEXT(D6,"yyyy-mm") -> 2025-10 | P6: first row of every source
A7: B0 | B7: 9589 | C7: BANK_CURRENT | D7: 45962 | E7: -15 | F7: mobile provider | G7: OUT_FIXED | H7: FIXED_COSTS | I7: phone_internet | N7: =IF(OR(K7="",M7=""),"",IF(C7="STATS_ONLY","stats",IF(ROUND(K7/M7,2)=E7,"OK","CHECK"))) | O7: =TEXT(D7,"yyyy-mm") -> 2025-11
A8: B0 | B8: 9590 | C8: BANK_CURRENT | D8: 45962 | E8: -100 | F8: monthly to pension savings | G8: TRANSFER | H8: TRANSFER | I8: transfer | N8: =IF(OR(K8="",M8=""),"",IF(C8="STATS_ONLY","stats",IF(ROUND(K8/M8,2)=E8,"OK","CHECK"))) | O8: =TEXT(D8,"yyyy-mm") -> 2025-11 | P8: leg out
A9: B0 | B9: 9590 | C9: BANK_PENSION | D9: 45962 | E9: 100 | F9: monthly to pension savings | G9: TRANSFER | H9: TRANSFER | I9: transfer | N9: =IF(OR(K9="",M9=""),"",IF(C9="STATS_ONLY","stats",IF(ROUND(K9/M9,2)=E9,"OK","CHECK"))) | O9: =TEXT(D9,"yyyy-mm") -> 2025-11 | P9: leg in
A10: B0 | B10: 9659 | C10: CREDIT_CARD | D10: 45963 | E10: -142 | F10: travel insurance winter | G10: OUT_ASIA_INSURANCE | H10: ASIA_PREP | I10: travel_insurance | N10: =IF(OR(K10="",M10=""),"",IF(C10="STATS_ONLY","stats",IF(ROUND(K10/M10,2)=E10,"OK","CHECK"))) | O10: =TEXT(D10,"yyyy-mm") -> 2025-11
A11: B0 | B11: 9009 | C11: CASH_AED | D11: 45965 | E11: -51.24 | F11: food and water at the airport | G11: OUT_ASIA | H11: ASIA_MISC | I11: airport | J11: s | K11: -220 | L11: AED | M11: 4.2935207 | N11: =IF(OR(K11="",M11=""),"",IF(C11="STATS_ONLY","stats",IF(ROUND(K11/M11,2)=E11,"OK","CHECK"))) -> OK | O11: =TEXT(D11,"yyyy-mm") -> 2025-11
A12: B0 | B12: 9657 | C12: BANK_CURRENT | D12: 45965 | E12: -18.9 | F12: airport train | G12: OUT | H12: TRAVEL_NL | I12: train | N12: =IF(OR(K12="",M12=""),"",IF(C12="STATS_ONLY","stats",IF(ROUND(K12/M12,2)=E12,"OK","CHECK"))) | O12: =TEXT(D12,"yyyy-mm") -> 2025-11
A13: B0 | B13: 9101 | C13: CASH_THB | D13: 45966 | E13: -176.1 | F13: room, month | G13: OUT_ASIA | H13: ASIA_DAILY | I13: housing | J13: h | K13: -6500 | L13: THB | M13: 36.910335 | N13: =IF(OR(K13="",M13=""),"",IF(C13="STATS_ONLY","stats",IF(ROUND(K13/M13,2)=E13,"OK","CHECK"))) -> OK | O13: =TEXT(D13,"yyyy-mm") -> 2025-11
A14: B0 | B14: 9102 | C14: CASH_THB | D14: 45966 | E14: -2.71 | F14: eggs and toast | G14: OUT_ASIA | H14: ASIA_DAILY | I14: daily_spending | J14: bf | K14: -100 | L14: THB | M14: 36.910335 | N14: =IF(OR(K14="",M14=""),"",IF(C14="STATS_ONLY","stats",IF(ROUND(K14/M14,2)=E14,"OK","CHECK"))) -> OK | O14: =TEXT(D14,"yyyy-mm") -> 2025-11
A15: B0 | B15: 9103 | C15: CASH_THB | D15: 45966 | E15: -2.84 | F15: massaman curry | G15: OUT_ASIA | H15: ASIA_DAILY | I15: daily_spending | J15: d | K15: -105 | L15: THB | M15: 36.910335 | N15: =IF(OR(K15="",M15=""),"",IF(C15="STATS_ONLY","stats",IF(ROUND(K15/M15,2)=E15,"OK","CHECK"))) -> OK | O15: =TEXT(D15,"yyyy-mm") -> 2025-11
A16: B0 | B16: 9104 | C16: CASH_THB | D16: 45966 | E16: -1.63 | F16: americano | G16: OUT_ASIA | H16: ASIA_DAILY | I16: daily_spending | J16: c | K16: -60 | L16: THB | M16: 36.910335 | N16: =IF(OR(K16="",M16=""),"",IF(C16="STATS_ONLY","stats",IF(ROUND(K16/M16,2)=E16,"OK","CHECK"))) -> OK | O16: =TEXT(D16,"yyyy-mm") -> 2025-11
A17: B0 | B17: 9591 | C17: BANK_CURRENT | D17: 45966 | E17: -45 | F17: storage unit | G17: OUT_FIXED | H17: FIXED_COSTS | I17: storage_unit | N17: =IF(OR(K17="",M17=""),"",IF(C17="STATS_ONLY","stats",IF(ROUND(K17/M17,2)=E17,"OK","CHECK"))) | O17: =TEXT(D17,"yyyy-mm") -> 2025-11
A18: B0 | B18: 9105 | C18: BANK_CURRENT | D18: 45967 | E18: -277.18 | F18: ATM withdrawal 277.18 EUR = 10,250 THB (10,000 + 250 fee) | G18: TRANSFER | H18: TRANSFER | I18: transfer | N18: =IF(OR(K18="",M18=""),"",IF(C18="STATS_ONLY","stats",IF(ROUND(K18/M18,2)=E18,"OK","CHECK"))) | O18: =TEXT(D18,"yyyy-mm") -> 2025-11 | P18: leg out
A19: B0 | B19: 9105 | C19: CASH_THB | D19: 45967 | E19: 277.18 | F19: ATM withdrawal 277.18 EUR = 10,250 THB (10,000 + 250 fee) | G19: TRANSFER | H19: TRANSFER | I19: transfer | J19: in | K19: 10250 | L19: THB | M19: =K19/E19 -> 36.97958 | N19: =IF(OR(K19="",M19=""),"",IF(C19="STATS_ONLY","stats",IF(ROUND(K19/M19,2)=E19,"OK","CHECK"))) -> OK | O19: =TEXT(D19,"yyyy-mm") -> 2025-11 | P19: leg in
A20: B0 | B20: 9105 | C20: CASH_THB | D20: 45967 | E20: -6.76 | F20: ATM fee 250 THB | G20: OUT_ASIA | H20: ASIA_DAILY | I20: bank_fees_asia | J20: misc | K20: -250 | L20: THB | M20: 36.97958 | N20: =IF(OR(K20="",M20=""),"",IF(C20="STATS_ONLY","stats",IF(ROUND(K20/M20,2)=E20,"OK","CHECK"))) -> OK | O20: =TEXT(D20,"yyyy-mm") -> 2025-11 | P20: cost split off, same id, negative
A21: B0 | B21: 9106 | C21: CASH_THB | D21: 45967 | E21: -2.16 | F21: noodle soup | G21: OUT_ASIA | H21: ASIA_DAILY | I21: daily_spending | J21: l | K21: -80 | L21: THB | M21: 36.97958 | N21: =IF(OR(K21="",M21=""),"",IF(C21="STATS_ONLY","stats",IF(ROUND(K21/M21,2)=E21,"OK","CHECK"))) -> OK | O21: =TEXT(D21,"yyyy-mm") -> 2025-11
A22: B0 | B22: 9107 | C22: CASH_THB | D22: 45967 | E22: -4.46 | F22: massaman curry | G22: OUT_ASIA | H22: ASIA_DAILY | I22: daily_spending | J22: d | K22: -165 | L22: THB | M22: 36.97958 | N22: =IF(OR(K22="",M22=""),"",IF(C22="STATS_ONLY","stats",IF(ROUND(K22/M22,2)=E22,"OK","CHECK"))) -> OK | O22: =TEXT(D22,"yyyy-mm") -> 2025-11
A23: B0 | B23: 9002 | C23: CASH_THB | D23: 45968 | E23: -2.71 | F23: pad thai | G23: OUT_ASIA | H23: ASIA_DAILY | I23: daily_spending | J23: d | K23: -100 | L23: THB | M23: 36.910335 | N23: =IF(OR(K23="",M23=""),"",IF(C23="STATS_ONLY","stats",IF(ROUND(K23/M23,2)=E23,"OK","CHECK"))) -> OK | O23: =TEXT(D23,"yyyy-mm") -> 2025-11
A24: B0 | B24: 9003 | C24: CASH_THB | D24: 45968 | E24: -1.63 | F24: iced latte | G24: OUT_ASIA | H24: ASIA_DAILY | I24: daily_spending | J24: c | K24: -60 | L24: THB | M24: 36.910335 | N24: =IF(OR(K24="",M24=""),"",IF(C24="STATS_ONLY","stats",IF(ROUND(K24/M24,2)=E24,"OK","CHECK"))) -> OK | O24: =TEXT(D24,"yyyy-mm") -> 2025-11
A25: B0 | B25: 9108 | C25: CASH_THB | D25: 45968 | E25: -1.35 | F25: fruit shake | G25: OUT_ASIA | H25: ASIA_DAILY | I25: daily_spending | J25: s | K25: -50 | L25: THB | M25: 36.97958 | N25: =IF(OR(K25="",M25=""),"",IF(C25="STATS_ONLY","stats",IF(ROUND(K25/M25,2)=E25,"OK","CHECK"))) -> OK | O25: =TEXT(D25,"yyyy-mm") -> 2025-11
A26: B0 | B26: 9592 | C26: MULTI_EUR | D26: 45968 | E26: -21.78 | F26: AI assistant subscription | G26: OUT_FIXED | H26: FIXED_COSTS | I26: ai_tools | N26: =IF(OR(K26="",M26=""),"",IF(C26="STATS_ONLY","stats",IF(ROUND(K26/M26,2)=E26,"OK","CHECK"))) | O26: =TEXT(D26,"yyyy-mm") -> 2025-11
A27: B0 | B27: 9109 | C27: CASH_THB | D27: 45969 | E27: -2.84 | F27: fruit plate | G27: OUT_ASIA | H27: ASIA_DAILY | I27: daily_spending | J27: bf | K27: -105 | L27: THB | M27: 36.97958 | N27: =IF(OR(K27="",M27=""),"",IF(C27="STATS_ONLY","stats",IF(ROUND(K27/M27,2)=E27,"OK","CHECK"))) -> OK | O27: =TEXT(D27,"yyyy-mm") -> 2025-11
A28: B0 | B28: 9110 | C28: CASH_THB | D28: 45969 | E28: -2.03 | F28: fried rice | G28: OUT_ASIA | H28: ASIA_DAILY | I28: daily_spending | J28: l | K28: -75 | L28: THB | M28: 36.97958 | N28: =IF(OR(K28="",M28=""),"",IF(C28="STATS_ONLY","stats",IF(ROUND(K28/M28,2)=E28,"OK","CHECK"))) -> OK | O28: =TEXT(D28,"yyyy-mm") -> 2025-11
A29: B0 | B29: 9111 | C29: CASH_THB | D29: 45969 | E29: -3.52 | F29: massaman curry | G29: OUT_ASIA | H29: ASIA_DAILY | I29: daily_spending | J29: d | K29: -130 | L29: THB | M29: 36.97958 | N29: =IF(OR(K29="",M29=""),"",IF(C29="STATS_ONLY","stats",IF(ROUND(K29/M29,2)=E29,"OK","CHECK"))) -> OK | O29: =TEXT(D29,"yyyy-mm") -> 2025-11
A30: B0 | B30: 9112 | C30: CASH_THB | D30: 45969 | E30: -1.76 | F30: espresso | G30: OUT_ASIA | H30: ASIA_DAILY | I30: daily_spending | J30: c | K30: -65 | L30: THB | M30: 36.97958 | N30: =IF(OR(K30="",M30=""),"",IF(C30="STATS_ONLY","stats",IF(ROUND(K30/M30,2)=E30,"OK","CHECK"))) -> OK | O30: =TEXT(D30,"yyyy-mm") -> 2025-11
A31: B0 | B31: 9593 | C31: BANK_CURRENT | D31: 45969 | E31: -2.99 | F31: cloud storage | G31: OUT_FIXED | H31: FIXED_COSTS | I31: cloud_storage | N31: =IF(OR(K31="",M31=""),"",IF(C31="STATS_ONLY","stats",IF(ROUND(K31/M31,2)=E31,"OK","CHECK"))) | O31: =TEXT(D31,"yyyy-mm") -> 2025-11
A32: B0 | B32: 9113 | C32: CASH_THB | D32: 45971 | E32: -3.52 | F32: fried rice | G32: OUT_ASIA | H32: ASIA_DAILY | I32: daily_spending | J32: l | K32: -130 | L32: THB | M32: 36.97958 | N32: =IF(OR(K32="",M32=""),"",IF(C32="STATS_ONLY","stats",IF(ROUND(K32/M32,2)=E32,"OK","CHECK"))) -> OK | O32: =TEXT(D32,"yyyy-mm") -> 2025-11
A33: B0 | B33: 9114 | C33: CASH_THB | D33: 45971 | E33: -1.49 | F33: flat white | G33: OUT_ASIA | H33: ASIA_DAILY | I33: daily_spending | J33: c | K33: -55 | L33: THB | M33: 36.97958 | N33: =IF(OR(K33="",M33=""),"",IF(C33="STATS_ONLY","stats",IF(ROUND(K33/M33,2)=E33,"OK","CHECK"))) -> OK | O33: =TEXT(D33,"yyyy-mm") -> 2025-11
A34: B0 | B34: 9115 | C34: CASH_THB | D34: 45971 | E34: -0.54 | F34: mango | G34: OUT_ASIA | H34: ASIA_DAILY | I34: daily_spending | J34: s | K34: -20 | L34: THB | M34: 36.97958 | N34: =IF(OR(K34="",M34=""),"",IF(C34="STATS_ONLY","stats",IF(ROUND(K34/M34,2)=E34,"OK","CHECK"))) -> OK | O34: =TEXT(D34,"yyyy-mm") -> 2025-11
A35: B0 | B35: 9116 | C35: CASH_THB | D35: 45972 | E35: -2.3 | F35: flat white | G35: OUT_ASIA | H35: ASIA_DAILY | I35: daily_spending | J35: c | K35: -85 | L35: THB | M35: 36.97958 | N35: =IF(OR(K35="",M35=""),"",IF(C35="STATS_ONLY","stats",IF(ROUND(K35/M35,2)=E35,"OK","CHECK"))) -> OK | O35: =TEXT(D35,"yyyy-mm") -> 2025-11
A36: B0 | B36: 9117 | C36: CASH_THB | D36: 45972 | E36: -1.62 | F36: mango | G36: OUT_ASIA | H36: ASIA_DAILY | I36: daily_spending | J36: s | K36: -60 | L36: THB | M36: 36.97958 | N36: =IF(OR(K36="",M36=""),"",IF(C36="STATS_ONLY","stats",IF(ROUND(K36/M36,2)=E36,"OK","CHECK"))) -> OK | O36: =TEXT(D36,"yyyy-mm") -> 2025-11
A37: B0 | B37: 9118 | C37: CASH_THB | D37: 45973 | E37: -2.84 | F37: eggs and toast | G37: OUT_ASIA | H37: ASIA_DAILY | I37: daily_spending | J37: bf | K37: -105 | L37: THB | M37: 36.97958 | N37: =IF(OR(K37="",M37=""),"",IF(C37="STATS_ONLY","stats",IF(ROUND(K37/M37,2)=E37,"OK","CHECK"))) -> OK | O37: =TEXT(D37,"yyyy-mm") -> 2025-11
A38: B0 | B38: 9119 | C38: CASH_THB | D38: 45973 | E38: -1.62 | F38: flat white | G38: OUT_ASIA | H38: ASIA_DAILY | I38: daily_spending | J38: c | K38: -60 | L38: THB | M38: 36.97958 | N38: =IF(OR(K38="",M38=""),"",IF(C38="STATS_ONLY","stats",IF(ROUND(K38/M38,2)=E38,"OK","CHECK"))) -> OK | O38: =TEXT(D38,"yyyy-mm") -> 2025-11
A39: B0 | B39: 9120 | C39: CASH_THB | D39: 45973 | E39: -3.38 | F39: sunscreen | G39: OUT_ASIA | H39: ASIA_DAILY | I39: daily_spending | J39: misc | K39: -125 | L39: THB | M39: 36.97958 | N39: =IF(OR(K39="",M39=""),"",IF(C39="STATS_ONLY","stats",IF(ROUND(K39/M39,2)=E39,"OK","CHECK"))) -> OK | O39: =TEXT(D39,"yyyy-mm") -> 2025-11
A40: B0 | B40: 9121 | C40: CASH_THB | D40: 45974 | E40: -1.89 | F40: smoothie bowl | G40: OUT_ASIA | H40: ASIA_DAILY | I40: daily_spending | J40: bf | K40: -70 | L40: THB | M40: 36.97958 | N40: =IF(OR(K40="",M40=""),"",IF(C40="STATS_ONLY","stats",IF(ROUND(K40/M40,2)=E40,"OK","CHECK"))) -> OK | O40: =TEXT(D40,"yyyy-mm") -> 2025-11
A41: B0 | B41: 9122 | C41: CASH_THB | D41: 45974 | E41: -3.38 | F41: noodle soup | G41: OUT_ASIA | H41: ASIA_DAILY | I41: daily_spending | J41: l | K41: -125 | L41: THB | M41: 36.97958 | N41: =IF(OR(K41="",M41=""),"",IF(C41="STATS_ONLY","stats",IF(ROUND(K41/M41,2)=E41,"OK","CHECK"))) -> OK | O41: =TEXT(D41,"yyyy-mm") -> 2025-11
A42: B0 | B42: 9123 | C42: CASH_THB | D42: 45974 | E42: -4.06 | F42: vegan buffet | G42: OUT_ASIA | H42: ASIA_DAILY | I42: daily_spending | J42: d | K42: -150 | L42: THB | M42: 36.97958 | N42: =IF(OR(K42="",M42=""),"",IF(C42="STATS_ONLY","stats",IF(ROUND(K42/M42,2)=E42,"OK","CHECK"))) -> OK | O42: =TEXT(D42,"yyyy-mm") -> 2025-11
A43: B0 | B43: 9124 | C43: CASH_THB | D43: 45974 | E43: -1.35 | F43: espresso | G43: OUT_ASIA | H43: ASIA_DAILY | I43: daily_spending | J43: c | K43: -50 | L43: THB | M43: 36.97958 | N43: =IF(OR(K43="",M43=""),"",IF(C43="STATS_ONLY","stats",IF(ROUND(K43/M43,2)=E43,"OK","CHECK"))) -> OK | O43: =TEXT(D43,"yyyy-mm") -> 2025-11
... A67: B0 | B67: 9147 | C67: CASH_THB | D67: 45981 | E67: -1.08 | F67: tip | G67: OUT_ASIA | H67: ASIA_DAILY | I67: daily_spending | J67: tip | K67: -40 | L67: THB | M67: 36.97958 | N67: =IF(OR(K67="",M67=""),"",IF(C67="STATS_ONLY","stats",IF(ROUND(K67/M67,2)=E67,"OK","CHECK"))) -> OK | O67: =TEXT(D67,"yyyy-mm") -> 2025-11
A68: B0 | B68: 9595 | C68: BANK_CURRENT | D68: 45981 | E68: -152 | F68: health insurer nv premium | G68: OUT_FIXED | H68: FIXED_COSTS | I68: health_insurance | N68: =IF(OR(K68="",M68=""),"",IF(C68="STATS_ONLY","stats",IF(ROUND(K68/M68,2)=E68,"OK","CHECK"))) | O68: =TEXT(D68,"yyyy-mm") -> 2025-11
A69: B0 | B69: 9596 | C69: BANK_CURRENT | D69: 45981 | E69: 131 | F69: tax office health allowance | G69: OUT_FIXED | H69: FIXED_COSTS | I69: health_insurance | N69: =IF(OR(K69="",M69=""),"",IF(C69="STATS_ONLY","stats",IF(ROUND(K69/M69,2)=E69,"OK","CHECK"))) | O69: =TEXT(D69,"yyyy-mm") -> 2025-11
A70: B0 | B70: 9148 | C70: CASH_THB | D70: 45982 | E70: -2.43 | F70: eggs and toast | G70: OUT_ASIA | H70: ASIA_DAILY | I70: daily_spending | J70: bf | K70: -90 | L70: THB | M70: 36.97958 | N70: =IF(OR(K70="",M70=""),"",IF(C70="STATS_ONLY","stats",IF(ROUND(K70/M70,2)=E70,"OK","CHECK"))) -> OK | O70: =TEXT(D70,"yyyy-mm") -> 2025-11
A71: B0 | B71: 9149 | C71: CASH_THB | D71: 45982 | E71: -2.7 | F71: som tam | G71: OUT_ASIA | H71: ASIA_DAILY | I71: daily_spending | J71: l | K71: -100 | L71: THB | M71: 36.97958 | N71: =IF(OR(K71="",M71=""),"",IF(C71="STATS_ONLY","stats",IF(ROUND(K71/M71,2)=E71,"OK","CHECK"))) -> OK | O71: =TEXT(D71,"yyyy-mm") -> 2025-11
A72: B0 | B72: 9150 | C72: CASH_THB | D72: 45982 | E72: -4.46 | F72: tofu stir fry | G72: OUT_ASIA | H72: ASIA_DAILY | I72: daily_spending | J72: d | K72: -165 | L72: THB | M72: 36.97958 | N72: =IF(OR(K72="",M72=""),"",IF(C72="STATS_ONLY","stats",IF(ROUND(K72/M72,2)=E72,"OK","CHECK"))) -> OK | O72: =TEXT(D72,"yyyy-mm") -> 2025-11
A73: B0 | B73: 9151 | C73: CASH_THB | D73: 45982 | E73: -4.19 | F73: ride-hailing | G73: OUT_ASIA | H73: ASIA_DAILY | I73: daily_spending | J73: taxi | K73: -155 | L73: THB | M73: 36.97958 | N73: =IF(OR(K73="",M73=""),"",IF(C73="STATS_ONLY","stats",IF(ROUND(K73/M73,2)=E73,"OK","CHECK"))) -> OK | O73: =TEXT(D73,"yyyy-mm") -> 2025-11
A74: B0 | B74: 9152 | C74: CASH_THB | D74: 45983 | E74: -2.97 | F74: pad see ew | G74: OUT_ASIA | H74: ASIA_DAILY | I74: daily_spending | J74: l | K74: -110 | L74: THB | M74: 36.97958 | N74: =IF(OR(K74="",M74=""),"",IF(C74="STATS_ONLY","stats",IF(ROUND(K74/M74,2)=E74,"OK","CHECK"))) -> OK | O74: =TEXT(D74,"yyyy-mm") -> 2025-11
A75: B0 | B75: 9153 | C75: CASH_THB | D75: 45983 | E75: -1.22 | F75: sticky rice | G75: OUT_ASIA | H75: ASIA_DAILY | I75: daily_spending | J75: s | K75: -45 | L75: THB | M75: 36.97958 | N75: =IF(OR(K75="",M75=""),"",IF(C75="STATS_ONLY","stats",IF(ROUND(K75/M75,2)=E75,"OK","CHECK"))) -> OK | O75: =TEXT(D75,"yyyy-mm") -> 2025-11
A76: B0 | B76: 9154 | C76: CASH_THB | D76: 45984 | E76: -2.84 | F76: muesli bowl | G76: OUT_ASIA | H76: ASIA_DAILY | I76: daily_spending | J76: bf | K76: -105 | L76: THB | M76: 36.97958 | N76: =IF(OR(K76="",M76=""),"",IF(C76="STATS_ONLY","stats",IF(ROUND(K76/M76,2)=E76,"OK","CHECK"))) -> OK | O76: =TEXT(D76,"yyyy-mm") -> 2025-11
A77: B0 | B77: 9155 | C77: CASH_THB | D77: 45984 | E77: -3.25 | F77: fried rice | G77: OUT_ASIA | H77: ASIA_DAILY | I77: daily_spending | J77: l | K77: -120 | L77: THB | M77: 36.97958 | N77: =IF(OR(K77="",M77=""),"",IF(C77="STATS_ONLY","stats",IF(ROUND(K77/M77,2)=E77,"OK","CHECK"))) -> OK | O77: =TEXT(D77,"yyyy-mm") -> 2025-11
A78: B0 | B78: 9156 | C78: CASH_THB | D78: 45984 | E78: -3.38 | F78: vegan buffet | G78: OUT_ASIA | H78: ASIA_DAILY | I78: daily_spending | J78: d | K78: -125 | L78: THB | M78: 36.97958 | N78: =IF(OR(K78="",M78=""),"",IF(C78="STATS_ONLY","stats",IF(ROUND(K78/M78,2)=E78,"OK","CHECK"))) -> OK | O78: =TEXT(D78,"yyyy-mm") -> 2025-11
A79: B0 | B79: 9157 | C79: CASH_THB | D79: 45984 | E79: -7.44 | F79: yoga class | G79: OUT_ASIA | H79: ASIA_DAILY | I79: daily_spending | J79: yoga | K79: -275 | L79: THB | M79: 36.97958 | N79: =IF(OR(K79="",M79=""),"",IF(C79="STATS_ONLY","stats",IF(ROUND(K79/M79,2)=E79,"OK","CHECK"))) -> OK | O79: =TEXT(D79,"yyyy-mm") -> 2025-11
A80: B0 | B80: 9594 | C80: BANK_CURRENT | D80: 45984 | E80: -7 | F80: office suite | G80: OUT_FIXED | H80: FIXED_COSTS | I80: office_suite | N80: =IF(OR(K80="",M80=""),"",IF(C80="STATS_ONLY","stats",IF(ROUND(K80/M80,2)=E80,"OK","CHECK"))) | O80: =TEXT(D80,"yyyy-mm") -> 2025-11
A81: B0 | B81: 9158 | C81: CASH_THB | D81: 45985 | E81: -3.11 | F81: som tam | G81: OUT_ASIA | H81: ASIA_DAILY | I81: daily_spending | J81: l | K81: -115 | L81: THB | M81: 36.97958 | N81: =IF(OR(K81="",M81=""),"",IF(C81="STATS_ONLY","stats",IF(ROUND(K81/M81,2)=E81,"OK","CHECK"))) -> OK | O81: =TEXT(D81,"yyyy-mm") -> 2025-11
A82: B0 | B82: 9159 | C82: CASH_THB | D82: 45986 | E82: -2.7 | F82: muesli bowl | G82: OUT_ASIA | H82: ASIA_DAILY | I82: daily_spending | J82: bf | K82: -100 | L82: THB | M82: 36.97958 | N82: =IF(OR(K82="",M82=""),"",IF(C82="STATS_ONLY","stats",IF(ROUND(K82/M82,2)=E82,"OK","CHECK"))) -> OK | O82: =TEXT(D82,"yyyy-mm") -> 2025-11
A83: B0 | B83: 9160 | C83: CASH_THB | D83: 45986 | E83: -2.03 | F83: fried rice | G83: OUT_ASIA | H83: ASIA_DAILY | I83: daily_spending | J83: l | K83: -75 | L83: THB | M83: 36.97958 | N83: =IF(OR(K83="",M83=""),"",IF(C83="STATS_ONLY","stats",IF(ROUND(K83/M83,2)=E83,"OK","CHECK"))) -> OK | O83: =TEXT(D83,"yyyy-mm") -> 2025-11
A84: B0 | B84: 9161 | C84: CASH_THB | D84: 45986 | E84: -4.33 | F84: tofu stir fry | G84: OUT_ASIA | H84: ASIA_DAILY | I84: daily_spending | J84: d | K84: -160 | L84: THB | M84: 36.97958 | N84: =IF(OR(K84="",M84=""),"",IF(C84="STATS_ONLY","stats",IF(ROUND(K84/M84,2)=E84,"OK","CHECK"))) -> OK | O84: =TEXT(D84,"yyyy-mm") -> 2025-11
A85: B0 | B85: 9162 | C85: CASH_THB | D85: 45986 | E85: -1.76 | F85: iced latte | G85: OUT_ASIA | H85: ASIA_DAILY | I85: daily_spending | J85: c | K85: -65 | L85: THB | M85: 36.97958 | N85: =IF(OR(K85="",M85=""),"",IF(C85="STATS_ONLY","stats",IF(ROUND(K85/M85,2)=E85,"OK","CHECK"))) -> OK | O85: =TEXT(D85,"yyyy-mm") -> 2025-11
A86: B0 | B86: 9163 | C86: CASH_THB | D86: 45986 | E86: -1.89 | F86: laundry | G86: OUT_ASIA | H86: ASIA_DAILY | I86: daily_spending | J86: lndry | K86: -70 | L86: THB | M86: 36.97958 | N86: =IF(OR(K86="",M86=""),"",IF(C86="STATS_ONLY","stats",IF(ROUND(K86/M86,2)=E86,"OK","CHECK"))) -> OK | O86: =TEXT(D86,"yyyy-mm") -> 2025-11
A87: B0 | B87: 9164 | C87: CASH_THB | D87: 45987 | E87: -2.16 | F87: eggs and toast | G87: OUT_ASIA | H87: ASIA_DAILY | I87: daily_spending | J87: bf | K87: -80 | L87: THB | M87: 36.97958 | N87: =IF(OR(K87="",M87=""),"",IF(C87="STATS_ONLY","stats",IF(ROUND(K87/M87,2)=E87,"OK","CHECK"))) -> OK | O87: =TEXT(D87,"yyyy-mm") -> 2025-11
A88: B0 | B88: 9165 | C88: CASH_THB | D88: 45987 | E88: -2.03 | F88: noodle soup | G88: OUT_ASIA | H88: ASIA_DAILY | I88: daily_spending | J88: l | K88: -75 | L88: THB | M88: 36.97958 | N88: =IF(OR(K88="",M88=""),"",IF(C88="STATS_ONLY","stats",IF(ROUND(K88/M88,2)=E88,"OK","CHECK"))) -> OK | O88: =TEXT(D88,"yyyy-mm") -> 2025-11
A89: B0 | B89: 9166 | C89: CASH_THB | D89: 45987 | E89: -2.16 | F89: americano | G89: OUT_ASIA | H89: ASIA_DAILY | I89: daily_spending | J89: c | K89: -80 | L89: THB | M89: 36.97958 | N89: =IF(OR(K89="",M89=""),"",IF(C89="STATS_ONLY","stats",IF(ROUND(K89/M89,2)=E89,"OK","CHECK"))) -> OK | O89: =TEXT(D89,"yyyy-mm") -> 2025-11
A90: B0 | B90: 9167 | C90: CASH_THB | D90: 45987 | E90: -1.22 | F90: fruit shake | G90: OUT_ASIA | H90: ASIA_DAILY | I90: daily_spending | J90: s | K90: -45 | L90: THB | M90: 36.97958 | N90: =IF(OR(K90="",M90=""),"",IF(C90="STATS_ONLY","stats",IF(ROUND(K90/M90,2)=E90,"OK","CHECK"))) -> OK | O90: =TEXT(D90,"yyyy-mm") -> 2025-11
A91: B0 | B91: 9168 | C91: CASH_THB | D91: 45988 | E91: -1.76 | F91: fried rice | G91: OUT_ASIA | H91: ASIA_DAILY | I91: daily_spending | J91: l | K91: -65 | L91: THB | M91: 36.97958 | N91: =IF(OR(K91="",M91=""),"",IF(C91="STATS_ONLY","stats",IF(ROUND(K91/M91,2)=E91,"OK","CHECK"))) -> OK | O91: =TEXT(D91,"yyyy-mm") -> 2025-11
A92: B0 | B92: 9169 | C92: CASH_THB | D92: 45988 | E92: -3.65 | F92: tofu stir fry | G92: OUT_ASIA | H92: ASIA_DAILY | I92: daily_spending | J92: d | K92: -135 | L92: THB | M92: 36.97958 | N92: =IF(OR(K92="",M92=""),"",IF(C92="STATS_ONLY","stats",IF(ROUND(K92/M92,2)=E92,"OK","CHECK"))) -> OK | O92: =TEXT(D92,"yyyy-mm") -> 2025-11
... A96: B0 | B96: 9173 | C96: CASH_THB | D96: 45989 | E96: -2.97 | F96: pad see ew | G96: OUT_ASIA | H96: ASIA_DAILY | I96: daily_spending | J96: l | K96: -110 | L96: THB | M96: 36.97958 | N96: =IF(OR(K96="",M96=""),"",IF(C96="STATS_ONLY","stats",IF(ROUND(K96/M96,2)=E96,"OK","CHECK"))) -> OK | O96: =TEXT(D96,"yyyy-mm") -> 2025-11
A97: B0 | B97: 9710 | C97: BANK_CURRENT | D97: 45989 | E97: -142 | F97: card settlement, travel insurance | G97: TRANSFER | H97: TRANSFER | I97: transfer | N97: =IF(OR(K97="",M97=""),"",IF(C97="STATS_ONLY","stats",IF(ROUND(K97/M97,2)=E97,"OK","CHECK"))) | O97: =TEXT(D97,"yyyy-mm") -> 2025-11 | P97: leg out
A98: B0 | B98: 9710 | C98: CREDIT_CARD | D98: 45989 | E98: 142 | F98: card settlement, travel insurance | G98: TRANSFER | H98: TRANSFER | I98: transfer | N98: =IF(OR(K98="",M98=""),"",IF(C98="STATS_ONLY","stats",IF(ROUND(K98/M98,2)=E98,"OK","CHECK"))) | O98: =TEXT(D98,"yyyy-mm") -> 2025-11 | P98: leg in
A99: B0 | B99: 9174 | C99: CASH_THB | D99: 45990 | E99: -2.7 | F99: pad see ew | G99: OUT_ASIA | H99: ASIA_DAILY | I99: daily_spending | J99: l | K99: -100 | L99: THB | M99: 36.97958 | N99: =IF(OR(K99="",M99=""),"",IF(C99="STATS_ONLY","stats",IF(ROUND(K99/M99,2)=E99,"OK","CHECK"))) -> OK | O99: =TEXT(D99,"yyyy-mm") -> 2025-11
A100: B0 | B100: 9175 | C100: CASH_THB | D100: 45990 | E100: -2.03 | F100: iced latte | G100: OUT_ASIA | H100: ASIA_DAILY | I100: daily_spending | J100: c | K100: -75 | L100: THB | M100: 36.97958 | N100: =IF(OR(K100="",M100=""),"",IF(C100="STATS_ONLY","stats",IF(ROUND(K100/M100,2)=E100,"OK","CHECK"))) -> OK | O100: =TEXT(D100,"yyyy-mm") -> 2025-11
A101: B0 | B101: 9176 | C101: CASH_THB | D101: 45990 | E101: -1.89 | F101: sticky rice | G101: OUT_ASIA | H101: ASIA_DAILY | I101: daily_spending | J101: s | K101: -70 | L101: THB | M101: 36.97958 | N101: =IF(OR(K101="",M101=""),"",IF(C101="STATS_ONLY","stats",IF(ROUND(K101/M101,2)=E101,"OK","CHECK"))) -> OK | O101: =TEXT(D101,"yyyy-mm") -> 2025-11
A102: B0 | B102: 9177 | C102: CASH_THB | D102: 45990 | E102: -8.11 | F102: yoga class | G102: OUT_ASIA | H102: ASIA_DAILY | I102: daily_spending | J102: yoga | K102: -300 | L102: THB | M102: 36.97958 | N102: =IF(OR(K102="",M102=""),"",IF(C102="STATS_ONLY","stats",IF(ROUND(K102/M102,2)=E102,"OK","CHECK"))) -> OK | O102: =TEXT(D102,"yyyy-mm") -> 2025-11
A103: B0 | B103: 9178 | C103: CASH_THB | D103: 45991 | E103: -2.84 | F103: pad see ew | G103: OUT_ASIA | H103: ASIA_DAILY | I103: daily_spending | J103: l | K103: -105 | L103: THB | M103: 36.97958 | N103: =IF(OR(K103="",M103=""),"",IF(C103="STATS_ONLY","stats",IF(ROUND(K103/M103,2)=E103,"OK","CHECK"))) -> OK | O103: =TEXT(D103,"yyyy-mm") -> 2025-11
A104: B0 | B104: 9179 | C104: CASH_THB | D104: 45991 | E104: -3.65 | F104: massaman curry | G104: OUT_ASIA | H104: ASIA_DAILY | I104: daily_spending | J104: d | K104: -135 | L104: THB | M104: 36.97958 | N104: =IF(OR(K104="",M104=""),"",IF(C104="STATS_ONLY","stats",IF(ROUND(K104/M104,2)=E104,"OK","CHECK"))) -> OK | O104: =TEXT(D104,"yyyy-mm") -> 2025-11
A105: B0 | B105: 9180 | C105: CASH_THB | D105: 45991 | E105: -1.08 | F105: mango | G105: OUT_ASIA | H105: ASIA_DAILY | I105: daily_spending | J105: s | K105: -40 | L105: THB | M105: 36.97958 | N105: =IF(OR(K105="",M105=""),"",IF(C105="STATS_ONLY","stats",IF(ROUND(K105/M105,2)=E105,"OK","CHECK"))) -> OK | O105: =TEXT(D105,"yyyy-mm") -> 2025-11
A106: B0 | B106: 9181 | C106: CASH_THB | D106: 45992 | E106: -1.08 | F106: coconut | G106: OUT_ASIA | H106: ASIA_DAILY | I106: daily_spending | J106: s | K106: -40 | L106: THB | M106: 36.97958 | N106: =IF(OR(K106="",M106=""),"",IF(C106="STATS_ONLY","stats",IF(ROUND(K106/M106,2)=E106,"OK","CHECK"))) -> OK | O106: =TEXT(D106,"yyyy-mm") -> 2025-12
A107: B0 | B107: 9597 | C107: BANK_CURRENT | D107: 45992 | E107: -15 | F107: mobile provider | G107: OUT_FIXED | H107: FIXED_COSTS | I107: phone_internet | N107: =IF(OR(K107="",M107=""),"",IF(C107="STATS_ONLY","stats",IF(ROUND(K107/M107,2)=E107,"OK","CHECK"))) | O107: =TEXT(D107,"yyyy-mm") -> 2025-12
A108: B0 | B108: 9182 | C108: CASH_THB | D108: 45993 | E108: -3.65 | F108: fried rice | G108: OUT_ASIA | H108: ASIA_DAILY | I108: daily_spending | J108: l | K108: -135 | L108: THB | M108: 36.97958 | N108: =IF(OR(K108="",M108=""),"",IF(C108="STATS_ONLY","stats",IF(ROUND(K108/M108,2)=E108,"OK","CHECK"))) -> OK | O108: =TEXT(D108,"yyyy-mm") -> 2025-12
A109: B0 | B109: 9183 | C109: CASH_THB | D109: 45993 | E109: -4.19 | F109: pad thai | G109: OUT_ASIA | H109: ASIA_DAILY | I109: daily_spending | J109: d | K109: -155 | L109: THB | M109: 36.97958 | N109: =IF(OR(K109="",M109=""),"",IF(C109="STATS_ONLY","stats",IF(ROUND(K109/M109,2)=E109,"OK","CHECK"))) -> OK | O109: =TEXT(D109,"yyyy-mm") -> 2025-12
A110: B0 | B110: 9184 | C110: CASH_THB | D110: 45993 | E110: -2.16 | F110: espresso | G110: OUT_ASIA | H110: ASIA_DAILY | I110: daily_spending | J110: c | K110: -80 | L110: THB | M110: 36.97958 | N110: =IF(OR(K110="",M110=""),"",IF(C110="STATS_ONLY","stats",IF(ROUND(K110/M110,2)=E110,"OK","CHECK"))) -> OK | O110: =TEXT(D110,"yyyy-mm") -> 2025-12
A111: B0 | B111: 9185 | C111: CASH_THB | D111: 45993 | E111: -1.08 | F111: sticky rice | G111: OUT_ASIA | H111: ASIA_DAILY | I111: daily_spending | J111: s | K111: -40 | L111: THB | M111: 36.97958 | N111: =IF(OR(K111="",M111=""),"",IF(C111="STATS_ONLY","stats",IF(ROUND(K111/M111,2)=E111,"OK","CHECK"))) -> OK | O111: =TEXT(D111,"yyyy-mm") -> 2025-12
A112: B0 | B112: 9186 | C112: CASH_THB | D112: 45994 | E112: -2.43 | F112: khao soi | G112: OUT_ASIA | H112: ASIA_DAILY | I112: daily_spending | J112: d | K112: -90 | L112: THB | M112: 36.97958 | N112: =IF(OR(K112="",M112=""),"",IF(C112="STATS_ONLY","stats",IF(ROUND(K112/M112,2)=E112,"OK","CHECK"))) -> OK | O112: =TEXT(D112,"yyyy-mm") -> 2025-12
A113: B0 | B113: 9187 | C113: CASH_THB | D113: 45995 | E113: -1.89 | F113: green curry | G113: OUT_ASIA | H113: ASIA_DAILY | I113: daily_spending | J113: l | K113: -70 | L113: THB | M113: 36.97958 | N113: =IF(OR(K113="",M113=""),"",IF(C113="STATS_ONLY","stats",IF(ROUND(K113/M113,2)=E113,"OK","CHECK"))) -> OK | O113: =TEXT(D113,"yyyy-mm") -> 2025-12
A114: B0 | B114: 9188 | C114: CASH_THB | D114: 45995 | E114: -3.79 | F114: massaman curry | G114: OUT_ASIA | H114: ASIA_DAILY | I114: daily_spending | J114: d | K114: -140 | L114: THB | M114: 36.97958 | N114: =IF(OR(K114="",M114=""),"",IF(C114="STATS_ONLY","stats",IF(ROUND(K114/M114,2)=E114,"OK","CHECK"))) -> OK | O114: =TEXT(D114,"yyyy-mm") -> 2025-12
A115: B0 | B115: 9189 | C115: CASH_THB | D115: 45995 | E115: -1.89 | F115: sticky rice | G115: OUT_ASIA | H115: ASIA_DAILY | I115: daily_spending | J115: s | K115: -70 | L115: THB | M115: 36.97958 | N115: =IF(OR(K115="",M115=""),"",IF(C115="STATS_ONLY","stats",IF(ROUND(K115/M115,2)=E115,"OK","CHECK"))) -> OK | O115: =TEXT(D115,"yyyy-mm") -> 2025-12
A116: B0 | B116: 9190 | C116: CASH_THB | D116: 45996 | E116: -2.03 | F116: muesli bowl | G116: OUT_ASIA | H116: ASIA_DAILY | I116: daily_spending | J116: bf | K116: -75 | L116: THB | M116: 36.97958 | N116: =IF(OR(K116="",M116=""),"",IF(C116="STATS_ONLY","stats",IF(ROUND(K116/M116,2)=E116,"OK","CHECK"))) -> OK | O116: =TEXT(D116,"yyyy-mm") -> 2025-12
A117: B0 | B117: 9191 | C117: CASH_THB | D117: 45996 | E117: -3.65 | F117: massaman curry | G117: OUT_ASIA | H117: ASIA_DAILY | I117: daily_spending | J117: d | K117: -135 | L117: THB | M117: 36.97958 | N117: =IF(OR(K117="",M117=""),"",IF(C117="STATS_ONLY","stats",IF(ROUND(K117/M117,2)=E117,"OK","CHECK"))) -> OK | O117: =TEXT(D117,"yyyy-mm") -> 2025-12
A118: B0 | B118: 9192 | C118: CASH_THB | D118: 45996 | E118: -2.03 | F118: espresso | G118: OUT_ASIA | H118: ASIA_DAILY | I118: daily_spending | J118: c | K118: -75 | L118: THB | M118: 36.97958 | N118: =IF(OR(K118="",M118=""),"",IF(C118="STATS_ONLY","stats",IF(ROUND(K118/M118,2)=E118,"OK","CHECK"))) -> OK | O118: =TEXT(D118,"yyyy-mm") -> 2025-12
A119: B0 | B119: 9598 | C119: BANK_CURRENT | D119: 45996 | E119: -45 | F119: storage unit | G119: OUT_FIXED | H119: FIXED_COSTS | I119: storage_unit | N119: =IF(OR(K119="",M119=""),"",IF(C119="STATS_ONLY","stats",IF(ROUND(K119/M119,2)=E119,"OK","CHECK"))) | O119: =TEXT(D119,"yyyy-mm") -> 2025-12
A120: B0 | B120: 9193 | C120: BANK_CURRENT | D120: 45997 | E120: -277.2 | F120: ATM withdrawal 277.20 EUR = 10,250 THB (10,000 + 250 fee) | G120: TRANSFER | H120: TRANSFER | I120: transfer | N120: =IF(OR(K120="",M120=""),"",IF(C120="STATS_ONLY","stats",IF(ROUND(K120/M120,2)=E120,"OK","CHECK"))) | O120: =TEXT(D120,"yyyy-mm") -> 2025-12 | P120: leg out
A121: B0 | B121: 9193 | C121: CASH_THB | D121: 45997 | E121: 277.2 | F121: ATM withdrawal 277.20 EUR = 10,250 THB (10,000 + 250 fee) | G121: TRANSFER | H121: TRANSFER | I121: transfer | J121: in | K121: 10250 | L121: THB | M121: =K121/E121 -> 36.976912 | N121: =IF(OR(K121="",M121=""),"",IF(C121="STATS_ONLY","stats",IF(ROUND(K121/M121,2)=E121,"OK","CHECK"))) -> OK | O121: =TEXT(D121,"yyyy-mm") -> 2025-12 | P121: leg in
A122: B0 | B122: 9193 | C122: CASH_THB | D122: 45997 | E122: -6.76 | F122: ATM fee 250 THB | G122: OUT_ASIA | H122: ASIA_DAILY | I122: bank_fees_asia | J122: misc | K122: -250 | L122: THB | M122: 36.976912 | N122: =IF(OR(K122="",M122=""),"",IF(C122="STATS_ONLY","stats",IF(ROUND(K122/M122,2)=E122,"OK","CHECK"))) -> OK | O122: =TEXT(D122,"yyyy-mm") -> 2025-12 | P122: cost split off, same id, negative
A123: B0 | B123: 9194 | C123: CASH_THB | D123: 45997 | E123: -3.65 | F123: green curry | G123: OUT_ASIA | H123: ASIA_DAILY | I123: daily_spending | J123: l | K123: -135 | L123: THB | M123: 36.976912 | N123: =IF(OR(K123="",M123=""),"",IF(C123="STATS_ONLY","stats",IF(ROUND(K123/M123,2)=E123,"OK","CHECK"))) -> OK | O123: =TEXT(D123,"yyyy-mm") -> 2025-12
A124: B0 | B124: 9195 | C124: CASH_THB | D124: 45997 | E124: -4.06 | F124: tofu stir fry | G124: OUT_ASIA | H124: ASIA_DAILY | I124: daily_spending | J124: d | K124: -150 | L124: THB | M124: 36.976912 | N124: =IF(OR(K124="",M124=""),"",IF(C124="STATS_ONLY","stats",IF(ROUND(K124/M124,2)=E124,"OK","CHECK"))) -> OK | O124: =TEXT(D124,"yyyy-mm") -> 2025-12
A125: B0 | B125: 9196 | C125: CASH_THB | D125: 45997 | E125: -1.62 | F125: americano | G125: OUT_ASIA | H125: ASIA_DAILY | I125: daily_spending | J125: c | K125: -60 | L125: THB | M125: 36.976912 | N125: =IF(OR(K125="",M125=""),"",IF(C125="STATS_ONLY","stats",IF(ROUND(K125/M125,2)=E125,"OK","CHECK"))) -> OK | O125: =TEXT(D125,"yyyy-mm") -> 2025-12
A126: B0 | B126: 9197 | C126: CASH_THB | D126: 45997 | E126: -0.68 | F126: fruit shake | G126: OUT_ASIA | H126: ASIA_DAILY | I126: daily_spending | J126: s | K126: -25 | L126: THB | M126: 36.976912 | N126: =IF(OR(K126="",M126=""),"",IF(C126="STATS_ONLY","stats",IF(ROUND(K126/M126,2)=E126,"OK","CHECK"))) -> OK | O126: =TEXT(D126,"yyyy-mm") -> 2025-12
...

Sheet CHECKS
A1: Checks
A2: All formulas read ENTRIES. A check passes when its status reads OK.
A4: # | B4: check | C4: value | D4: status | E4: what a failure usually means
A5: 1 | B5: Sum of all TRANSFER rows | C5: =ROUND(SUMIFS(ENTRIES!$E$2:$E$2000,ENTRIES!$G$2:$G$2000,"TRANSFER"),2) -> 0 | D5: =IF(ABS(C5)<0.005,"OK","CHECK") -> OK | E5: A leg is missing, doubled or has the wrong sign
A6: 2 | B6: TRANSFER ids that do not sum to zero | C6: =COUNTIF($D$18:$D$78,"CHECK") -> 0 | D6: =IF(C6=0,"OK","CHECK") -> OK | E6: See the per-id table below for the exact pair
A7: 3 | B7: Months whose TRANSFER sum is not zero | C7: =COUNTIF($D$83:$D$91,"<>OK") -> 2 | D7: =IF(C7=0,"OK","REVIEW") -> REVIEW | E7: A pair with legs in different months (T09, T12): fine if explained
A8: 4 | B8: Helper sources not at zero | C8: =COUNTIFS($C$96:$C$121,"helper",$F$96:$F$121,"CHECK") -> 0 | D8: =IF(C8=0,"OK","CHECK") -> OK | E8: An open claim, tab or prepayment: fine if you know what it is
A9: 5 | B9: Rows where amount is not exactly ROUND(fx_amount / rate, 2) | C9: =COUNTIF(ENTRIES!$N$2:$N$2000,"CHECK") -> 0 | D9: =IF(C9=0,"OK","CHECK") -> OK | E9: A typo or a wrong sign; adjust the amount by hand so the difference is 0
A10: 6 | B10: Real sources vs statement, app or cash count | C10: manual | E10: Compare the balance table below with the outside world
A11: 7 | B11: Bank statement line by line | C11: manual | E11: Load the bank CSV in the reconciliation tool
A16: Check 2 · TRANSFER sum per id
A17: id | B17: case | C17: TRANSFER sum | D17: status | E17: rows
A18: 101 | B18: =INDEX(ENTRIES!$A$2:$A$2000,MATCH(A18,ENTRIES!$B$2:$B$2000,0)) -> T01 | C18: =ROUND(SUMIFS(ENTRIES!$E$2:$E$2000,ENTRIES!$B$2:$B$2000,A18,ENTRIES!$G$2:$G$2000,"TRANSFER"),2) -> 0 | D18: =IF(ABS(C18)<0.005,"OK","CHECK") -> OK | E18: =COUNTIFS(ENTRIES!$B$2:$B$2000,A18,ENTRIES!$G$2:$G$2000,"TRANSFER") -> 2
A19: 102 | B19: =INDEX(ENTRIES!$A$2:$A$2000,MATCH(A19,ENTRIES!$B$2:$B$2000,0)) -> T01 | C19: =ROUND(SUMIFS(ENTRIES!$E$2:$E$2000,ENTRIES!$B$2:$B$2000,A19,ENTRIES!$G$2:$G$2000,"TRANSFER"),2) -> 0 | D19: =IF(ABS(C19)<0.005,"OK","CHECK") -> OK | E19: =COUNTIFS(ENTRIES!$B$2:$B$2000,A19,ENTRIES!$G$2:$G$2000,"TRANSFER") -> 2
A20: 201 | B20: =INDEX(ENTRIES!$A$2:$A$2000,MATCH(A20,ENTRIES!$B$2:$B$2000,0)) -> T02 | C20: =ROUND(SUMIFS(ENTRIES!$E$2:$E$2000,ENTRIES!$B$2:$B$2000,A20,ENTRIES!$G$2:$G$2000,"TRANSFER"),2) -> 0 | D20: =IF(ABS(C20)<0.005,"OK","CHECK") -> OK | E20: =COUNTIFS(ENTRIES!$B$2:$B$2000,A20,ENTRIES!$G$2:$G$2000,"TRANSFER") -> 2
A21: 301 | B21: =INDEX(ENTRIES!$A$2:$A$2000,MATCH(A21,ENTRIES!$B$2:$B$2000,0)) -> T03 | C21: =ROUND(SUMIFS(ENTRIES!$E$2:$E$2000,ENTRIES!$B$2:$B$2000,A21,ENTRIES!$G$2:$G$2000,"TRANSFER"),2) -> 0 | D21: =IF(ABS(C21)<0.005,"OK","CHECK") -> OK | E21: =COUNTIFS(ENTRIES!$B$2:$B$2000,A21,ENTRIES!$G$2:$G$2000,"TRANSFER") -> 2
A22: 401 | B22: =INDEX(ENTRIES!$A$2:$A$2000,MATCH(A22,ENTRIES!$B$2:$B$2000,0)) -> T04 | C22: =ROUND(SUMIFS(ENTRIES!$E$2:$E$2000,ENTRIES!$B$2:$B$2000,A22,ENTRIES!$G$2:$G$2000,"TRANSFER"),2) -> 0 | D22: =IF(ABS(C22)<0.005,"OK","CHECK") -> OK | E22: =COUNTIFS(ENTRIES!$B$2:$B$2000,A22,ENTRIES!$G$2:$G$2000,"TRANSFER") -> 2
A23: 402 | B23: =INDEX(ENTRIES!$A$2:$A$2000,MATCH(A23,ENTRIES!$B$2:$B$2000,0)) -> T04 | C23: =ROUND(SUMIFS(ENTRIES!$E$2:$E$2000,ENTRIES!$B$2:$B$2000,A23,ENTRIES!$G$2:$G$2000,"TRANSFER"),2) -> 0 | D23: =IF(ABS(C23)<0.005,"OK","CHECK") -> OK | E23: =COUNTIFS(ENTRIES!$B$2:$B$2000,A23,ENTRIES!$G$2:$G$2000,"TRANSFER") -> 2
A24: 502 | B24: =INDEX(ENTRIES!$A$2:$A$2000,MATCH(A24,ENTRIES!$B$2:$B$2000,0)) -> T05 | C24: =ROUND(SUMIFS(ENTRIES!$E$2:$E$2000,ENTRIES!$B$2:$B$2000,A24,ENTRIES!$G$2:$G$2000,"TRANSFER"),2) -> 0 | D24: =IF(ABS(C24)<0.005,"OK","CHECK") -> OK | E24: =COUNTIFS(ENTRIES!$B$2:$B$2000,A24,ENTRIES!$G$2:$G$2000,"TRANSFER") -> 2
A25: 601 | B25: =INDEX(ENTRIES!$A$2:$A$2000,MATCH(A25,ENTRIES!$B$2:$B$2000,0)) -> T06 | C25: =ROUND(SUMIFS(ENTRIES!$E$2:$E$2000,ENTRIES!$B$2:$B$2000,A25,ENTRIES!$G$2:$G$2000,"TRANSFER"),2) -> 0 | D25: =IF(ABS(C25)<0.005,"OK","CHECK") -> OK | E25: =COUNTIFS(ENTRIES!$B$2:$B$2000,A25,ENTRIES!$G$2:$G$2000,"TRANSFER") -> 2
A26: 701 | B26: =INDEX(ENTRIES!$A$2:$A$2000,MATCH(A26,ENTRIES!$B$2:$B$2000,0)) -> T07 | C26: =ROUND(SUMIFS(ENTRIES!$E$2:$E$2000,ENTRIES!$B$2:$B$2000,A26,ENTRIES!$G$2:$G$2000,"TRANSFER"),2) -> 0 | D26: =IF(ABS(C26)<0.005,"OK","CHECK") -> OK | E26: =COUNTIFS(ENTRIES!$B$2:$B$2000,A26,ENTRIES!$G$2:$G$2000,"TRANSFER") -> 2
A27: 801 | B27: =INDEX(ENTRIES!$A$2:$A$2000,MATCH(A27,ENTRIES!$B$2:$B$2000,0)) -> T08 | C27: =ROUND(SUMIFS(ENTRIES!$E$2:$E$2000,ENTRIES!$B$2:$B$2000,A27,ENTRIES!$G$2:$G$2000,"TRANSFER"),2) -> 0 | D27: =IF(ABS(C27)<0.005,"OK","CHECK") -> OK | E27: =COUNTIFS(ENTRIES!$B$2:$B$2000,A27,ENTRIES!$G$2:$G$2000,"TRANSFER") -> 2
A28: 901 | B28: =INDEX(ENTRIES!$A$2:$A$2000,MATCH(A28,ENTRIES!$B$2:$B$2000,0)) -> T09 | C28: =ROUND(SUMIFS(ENTRIES!$E$2:$E$2000,ENTRIES!$B$2:$B$2000,A28,ENTRIES!$G$2:$G$2000,"TRANSFER"),2) -> 0 | D28: =IF(ABS(C28)<0.005,"OK","CHECK") -> OK | E28: =COUNTIFS(ENTRIES!$B$2:$B$2000,A28,ENTRIES!$G$2:$G$2000,"TRANSFER") -> 2
A29: 1001 | B29: =INDEX(ENTRIES!$A$2:$A$2000,MATCH(A29,ENTRIES!$B$2:$B$2000,0)) -> T10 | C29: =ROUND(SUMIFS(ENTRIES!$E$2:$E$2000,ENTRIES!$B$2:$B$2000,A29,ENTRIES!$G$2:$G$2000,"TRANSFER"),2) -> 0 | D29: =IF(ABS(C29)<0.005,"OK","CHECK") -> OK | E29: =COUNTIFS(ENTRIES!$B$2:$B$2000,A29,ENTRIES!$G$2:$G$2000,"TRANSFER") -> 2
... A78: 9710 | B78: =INDEX(ENTRIES!$A$2:$A$2000,MATCH(A78,ENTRIES!$B$2:$B$2000,0)) -> B0 | C78: =ROUND(SUMIFS(ENTRIES!$E$2:$E$2000,ENTRIES!$B$2:$B$2000,A78,ENTRIES!$G$2:$G$2000,"TRANSFER"),2) -> 0 | D78: =IF(ABS(C78)<0.005,"OK","CHECK") -> OK | E78: =COUNTIFS(ENTRIES!$B$2:$B$2000,A78,ENTRIES!$G$2:$G$2000,"TRANSFER") -> 2
A81: Check 3 · TRANSFER sum per month
A82: month | C82: TRANSFER sum | D82: status | E82: explanation when not zero
A83: 2025-10 | C83: =ROUND(SUMIFS(ENTRIES!$E$2:$E$2000,ENTRIES!$O$2:$O$2000,A83,ENTRIES!$G$2:$G$2000,"TRANSFER"),2) -> 0 | D83: =IF(ABS(C83)<0.005,"OK","REVIEW") -> OK | E83: =IF(D83="OK","","Look for pairs with legs in different months")
A84: 2025-11 | C84: =ROUND(SUMIFS(ENTRIES!$E$2:$E$2000,ENTRIES!$O$2:$O$2000,A84,ENTRIES!$G$2:$G$2000,"TRANSFER"),2) -> 0 | D84: =IF(ABS(C84)<0.005,"OK","REVIEW") -> OK | E84: =IF(D84="OK","","Look for pairs with legs in different months")
A85: 2025-12 | C85: =ROUND(SUMIFS(ENTRIES!$E$2:$E$2000,ENTRIES!$O$2:$O$2000,A85,ENTRIES!$G$2:$G$2000,"TRANSFER"),2) -> 0 | D85: =IF(ABS(C85)<0.005,"OK","REVIEW") -> OK | E85: =IF(D85="OK","","Look for pairs with legs in different months")
A86: 2026-01 | C86: =ROUND(SUMIFS(ENTRIES!$E$2:$E$2000,ENTRIES!$O$2:$O$2000,A86,ENTRIES!$G$2:$G$2000,"TRANSFER"),2) -> -500 | D86: =IF(ABS(C86)<0.005,"OK","REVIEW") -> REVIEW | E86: =IF(D86="OK","","Look for pairs with legs in different months") -> Look for pairs with legs in different months
A87: 2026-02 | C87: =ROUND(SUMIFS(ENTRIES!$E$2:$E$2000,ENTRIES!$O$2:$O$2000,A87,ENTRIES!$G$2:$G$2000,"TRANSFER"),2) -> 500 | D87: =IF(ABS(C87)<0.005,"OK","REVIEW") -> REVIEW | E87: =IF(D87="OK","","Look for pairs with legs in different months") -> Look for pairs with legs in different months
A88: 2026-03 | C88: =ROUND(SUMIFS(ENTRIES!$E$2:$E$2000,ENTRIES!$O$2:$O$2000,A88,ENTRIES!$G$2:$G$2000,"TRANSFER"),2) -> 0 | D88: =IF(ABS(C88)<0.005,"OK","REVIEW") -> OK | E88: =IF(D88="OK","","Look for pairs with legs in different months")
A89: 2026-04 | C89: =ROUND(SUMIFS(ENTRIES!$E$2:$E$2000,ENTRIES!$O$2:$O$2000,A89,ENTRIES!$G$2:$G$2000,"TRANSFER"),2) -> 0 | D89: =IF(ABS(C89)<0.005,"OK","REVIEW") -> OK | E89: =IF(D89="OK","","Look for pairs with legs in different months")
A90: 2026-05 | C90: =ROUND(SUMIFS(ENTRIES!$E$2:$E$2000,ENTRIES!$O$2:$O$2000,A90,ENTRIES!$G$2:$G$2000,"TRANSFER"),2) -> 0 | D90: =IF(ABS(C90)<0.005,"OK","REVIEW") -> OK | E90: =IF(D90="OK","","Look for pairs with legs in different months")
A91: 2026-06 | C91: =ROUND(SUMIFS(ENTRIES!$E$2:$E$2000,ENTRIES!$O$2:$O$2000,A91,ENTRIES!$G$2:$G$2000,"TRANSFER"),2) -> 0 | D91: =IF(ABS(C91)<0.005,"OK","REVIEW") -> OK | E91: =IF(D91="OK","","Look for pairs with legs in different months")
A94: Checks 4 and 6 · balance per source
A95: source | B95: what it is | C95: kind | D95: balance € | E95: local balance | F95: status
A96: BANK_CURRENT | B96: Current account | C96: =INDEX(CODES!$G$5:$G$30,MATCH(A96,CODES!$F$5:$F$30,0)) -> real | D96: =ROUND(SUMIFS(ENTRIES!$E$2:$E$2000,ENTRIES!$C$2:$C$2000,A96),2) -> 5373.96 | E96: =IF(LEFT(A96,5)="CASH_",IF(A96="CASH_EUR","",SUMIFS(ENTRIES!$K$2:$K$2000,ENTRIES!$C$2:$C$2000,A96)),IF(A96="MULTI_THB",SUMIFS(ENTRIES!$K$2:$K$2000,ENTRIES!$C$2:$C$2000,A96),"")) | F96: =IF(C96="helper",IF(ABS(D96)<0.005,"OK","CHECK"),"compare") -> compare
A97: BANK_SAVINGS | B97: Savings account | C97: =INDEX(CODES!$G$5:$G$30,MATCH(A97,CODES!$F$5:$F$30,0)) -> real | D97: =ROUND(SUMIFS(ENTRIES!$E$2:$E$2000,ENTRIES!$C$2:$C$2000,A97),2) -> 8485.3 | E97: =IF(LEFT(A97,5)="CASH_",IF(A97="CASH_EUR","",SUMIFS(ENTRIES!$K$2:$K$2000,ENTRIES!$C$2:$C$2000,A97)),IF(A97="MULTI_THB",SUMIFS(ENTRIES!$K$2:$K$2000,ENTRIES!$C$2:$C$2000,A97),"")) | F97: =IF(C97="helper",IF(ABS(D97)<0.005,"OK","CHECK"),"compare") -> compare
A98: BANK_PENSION | B98: Pension savings, locked until retirement | C98: =INDEX(CODES!$G$5:$G$30,MATCH(A98,CODES!$F$5:$F$30,0)) -> real | D98: =ROUND(SUMIFS(ENTRIES!$E$2:$E$2000,ENTRIES!$C$2:$C$2000,A98),2) -> 3200 | E98: =IF(LEFT(A98,5)="CASH_",IF(A98="CASH_EUR","",SUMIFS(ENTRIES!$K$2:$K$2000,ENTRIES!$C$2:$C$2000,A98)),IF(A98="MULTI_THB",SUMIFS(ENTRIES!$K$2:$K$2000,ENTRIES!$C$2:$C$2000,A98),"")) | F98: =IF(C98="helper",IF(ABS(D98)<0.005,"OK","CHECK"),"compare") -> compare
A99: CREDIT_CARD | B99: Credit card | C99: =INDEX(CODES!$G$5:$G$30,MATCH(A99,CODES!$F$5:$F$30,0)) -> real | D99: =ROUND(SUMIFS(ENTRIES!$E$2:$E$2000,ENTRIES!$C$2:$C$2000,A99),2) -> -49.14 | E99: =IF(LEFT(A99,5)="CASH_",IF(A99="CASH_EUR","",SUMIFS(ENTRIES!$K$2:$K$2000,ENTRIES!$C$2:$C$2000,A99)),IF(A99="MULTI_THB",SUMIFS(ENTRIES!$K$2:$K$2000,ENTRIES!$C$2:$C$2000,A99),"")) | F99: =IF(C99="helper",IF(ABS(D99)<0.005,"OK","CHECK"),"compare") -> compare
A100: FOREIGN_BANK | B100: Small account abroad | C100: =INDEX(CODES!$G$5:$G$30,MATCH(A100,CODES!$F$5:$F$30,0)) -> real | D100: =ROUND(SUMIFS(ENTRIES!$E$2:$E$2000,ENTRIES!$C$2:$C$2000,A100),2) -> 149.5 | E100: =IF(LEFT(A100,5)="CASH_",IF(A100="CASH_EUR","",SUMIFS(ENTRIES!$K$2:$K$2000,ENTRIES!$C$2:$C$2000,A100)),IF(A100="MULTI_THB",SUMIFS(ENTRIES!$K$2:$K$2000,ENTRIES!$C$2:$C$2000,A100),"")) | F100: =IF(C100="helper",IF(ABS(D100)<0.005,"OK","CHECK"),"compare") -> compare
A101: MULTI_EUR | B101: Multi-currency app, EUR pocket | C101: =INDEX(CODES!$G$5:$G$30,MATCH(A101,CODES!$F$5:$F$30,0)) -> real | D101: =ROUND(SUMIFS(ENTRIES!$E$2:$E$2000,ENTRIES!$C$2:$C$2000,A101),2) -> 375.76 | E101: =IF(LEFT(A101,5)="CASH_",IF(A101="CASH_EUR","",SUMIFS(ENTRIES!$K$2:$K$2000,ENTRIES!$C$2:$C$2000,A101)),IF(A101="MULTI_THB",SUMIFS(ENTRIES!$K$2:$K$2000,ENTRIES!$C$2:$C$2000,A101),"")) | F101: =IF(C101="helper",IF(ABS(D101)<0.005,"OK","CHECK"),"compare") -> compare
A102: MULTI_THB | B102: Multi-currency app, THB pocket | C102: =INDEX(CODES!$G$5:$G$30,MATCH(A102,CODES!$F$5:$F$30,0)) -> real | D102: =ROUND(SUMIFS(ENTRIES!$E$2:$E$2000,ENTRIES!$C$2:$C$2000,A102),2) -> 251.11 | E102: =IF(LEFT(A102,5)="CASH_",IF(A102="CASH_EUR","",SUMIFS(ENTRIES!$K$2:$K$2000,ENTRIES!$C$2:$C$2000,A102)),IF(A102="MULTI_THB",SUMIFS(ENTRIES!$K$2:$K$2000,ENTRIES!$C$2:$C$2000,A102),"")) -> 9254 | F102: =IF(C102="helper",IF(ABS(D102)<0.005,"OK","CHECK"),"compare") -> compare
A103: BANK_ONLINE | B103: Online bank / money-transfer service | C103: =INDEX(CODES!$G$5:$G$30,MATCH(A103,CODES!$F$5:$F$30,0)) -> real | D103: =ROUND(SUMIFS(ENTRIES!$E$2:$E$2000,ENTRIES!$C$2:$C$2000,A103),2) -> 0 | E103: =IF(LEFT(A103,5)="CASH_",IF(A103="CASH_EUR","",SUMIFS(ENTRIES!$K$2:$K$2000,ENTRIES!$C$2:$C$2000,A103)),IF(A103="MULTI_THB",SUMIFS(ENTRIES!$K$2:$K$2000,ENTRIES!$C$2:$C$2000,A103),"")) | F103: =IF(C103="helper",IF(ABS(D103)<0.005,"OK","CHECK"),"compare") -> compare
A104: ONLINE_WALLET | B104: Online payment wallet | C104: =INDEX(CODES!$G$5:$G$30,MATCH(A104,CODES!$F$5:$F$30,0)) -> real | D104: =ROUND(SUMIFS(ENTRIES!$E$2:$E$2000,ENTRIES!$C$2:$C$2000,A104),2) -> 0 | E104: =IF(LEFT(A104,5)="CASH_",IF(A104="CASH_EUR","",SUMIFS(ENTRIES!$K$2:$K$2000,ENTRIES!$C$2:$C$2000,A104)),IF(A104="MULTI_THB",SUMIFS(ENTRIES!$K$2:$K$2000,ENTRIES!$C$2:$C$2000,A104),"")) | F104: =IF(C104="helper",IF(ABS(D104)<0.005,"OK","CHECK"),"compare") -> compare
A105: CASH_EUR | B105: Cash, euro | C105: =INDEX(CODES!$G$5:$G$30,MATCH(A105,CODES!$F$5:$F$30,0)) -> real | D105: =ROUND(SUMIFS(ENTRIES!$E$2:$E$2000,ENTRIES!$C$2:$C$2000,A105),2) -> 242 | E105: =IF(LEFT(A105,5)="CASH_",IF(A105="CASH_EUR","",SUMIFS(ENTRIES!$K$2:$K$2000,ENTRIES!$C$2:$C$2000,A105)),IF(A105="MULTI_THB",SUMIFS(ENTRIES!$K$2:$K$2000,ENTRIES!$C$2:$C$2000,A105),"")) | F105: =IF(C105="helper",IF(ABS(D105)<0.005,"OK","CHECK"),"compare") -> compare
A106: CASH_THB | B106: Cash, Thai baht | C106: =INDEX(CODES!$G$5:$G$30,MATCH(A106,CODES!$F$5:$F$30,0)) -> real | D106: =ROUND(SUMIFS(ENTRIES!$E$2:$E$2000,ENTRIES!$C$2:$C$2000,A106),2) -> 93.94 | E106: =IF(LEFT(A106,5)="CASH_",IF(A106="CASH_EUR","",SUMIFS(ENTRIES!$K$2:$K$2000,ENTRIES!$C$2:$C$2000,A106)),IF(A106="MULTI_THB",SUMIFS(ENTRIES!$K$2:$K$2000,ENTRIES!$C$2:$C$2000,A106),"")) -> 3473 | F106: =IF(C106="helper",IF(ABS(D106)<0.005,"OK","CHECK"),"compare") -> compare
A107: CASH_VND | B107: Cash, Vietnamese dong | C107: =INDEX(CODES!$G$5:$G$30,MATCH(A107,CODES!$F$5:$F$30,0)) -> real | D107: =ROUND(SUMIFS(ENTRIES!$E$2:$E$2000,ENTRIES!$C$2:$C$2000,A107),2) -> 16.61 | E107: =IF(LEFT(A107,5)="CASH_",IF(A107="CASH_EUR","",SUMIFS(ENTRIES!$K$2:$K$2000,ENTRIES!$C$2:$C$2000,A107)),IF(A107="MULTI_THB",SUMIFS(ENTRIES!$K$2:$K$2000,ENTRIES!$C$2:$C$2000,A107),"")) -> 455000 | F107: =IF(C107="helper",IF(ABS(D107)<0.005,"OK","CHECK"),"compare") -> compare
... A121: STATS_ONLY | B121: Zero-amount rows with local details | C121: =INDEX(CODES!$G$5:$G$30,MATCH(A121,CODES!$F$5:$F$30,0)) -> helper | D121: =ROUND(SUMIFS(ENTRIES!$E$2:$E$2000,ENTRIES!$C$2:$C$2000,A121),2) -> 0 | E121: =IF(LEFT(A121,5)="CASH_",IF(A121="CASH_EUR","",SUMIFS(ENTRIES!$K$2:$K$2000,ENTRIES!$C$2:$C$2000,A121)),IF(A121="MULTI_THB",SUMIFS(ENTRIES!$K$2:$K$2000,ENTRIES!$C$2:$C$2000,A121),"")) | F121: =IF(C121="helper",IF(ABS(D121)<0.005,"OK","CHECK"),"compare") -> OK
B122: Local balance = sum of fx_amount, to compare with counted cash or the app pocket.

Sheet SUMMARY
A1: Summary
A2: Income, spending and net worth from ENTRIES. TRANSFER rows change none of these totals.
A4: line | B4: €
A5: Opening balances | B5: =SUMIFS(ENTRIES!$E$2:$E$2000,ENTRIES!$G$2:$G$2000,"OPENING_BALANCE") -> 17201.24
A6: Income (IN) | B6: =SUMIFS(ENTRIES!$E$2:$E$2000,ENTRIES!$G$2:$G$2000,"IN") -> 6407.3
A7: Spending, Europe (OUT) | B7: =SUMIFS(ENTRIES!$E$2:$E$2000,ENTRIES!$G$2:$G$2000,"OUT") -> -1059.25
A8: Spending, fixed (OUT_FIXED) | B8: =SUMIFS(ENTRIES!$E$2:$E$2000,ENTRIES!$G$2:$G$2000,"OUT_FIXED") -> -985.66
A9: Spending, Asia (OUT_ASIA*) | B9: =SUMIFS(ENTRIES!$E$2:$E$2000,ENTRIES!$G$2:$G$2000,"OUT_ASIA")+SUMIFS(ENTRIES!$E$2:$E$2000,ENTRIES!$G$2:$G$2000,"OUT_ASIA_FLIGHTS")+SUMIFS(ENTRIES!$E$2:$E$2000,ENTRIES!$G$2:$G$2000,"OUT_ASIA_INSURANCE")+SUMIFS(ENTRIES!$E$2:$E$2000,ENTRIES!$G$2:$G$2000,"OUT_ASIA_PREPAID") -> -3274.59
A10: Paper gains and losses | B10: =SUMIFS(ENTRIES!$E$2:$E$2000,ENTRIES!$G$2:$G$2000,"PAPER_GAIN_LOSS") -> -11.8
A11: Transfers (must be 0) | B11: =SUMIFS(ENTRIES!$E$2:$E$2000,ENTRIES!$G$2:$G$2000,"TRANSFER") -> 0
A12: Uncategorised | B12: =SUMIFS(ENTRIES!$E$2:$E$2000,ENTRIES!$G$2:$G$2000,"UNCATEGORISED") -> 0
A13: Net worth now (sum of all rows) | B13: =SUM(ENTRIES!$E$2:$E$2000) -> 18277.24
A14: Net worth from the lines above | B14: =SUM(B5:B12) -> 18277.24
A15: Difference (must be 0) | B15: =ROUND(B13-B14,2) -> 0
A17: Per month (sign of amount: costs are negative)
A18: month | B18: income | C18: Europe | D18: fixed | E18: Asia | F18: total spending | G18: transfers
A19: 2025-10 | B19: =SUMIFS(ENTRIES!$E$2:$E$2000,ENTRIES!$O$2:$O$2000,A19,ENTRIES!$G$2:$G$2000,"IN") -> 0 | C19: =SUMIFS(ENTRIES!$E$2:$E$2000,ENTRIES!$O$2:$O$2000,A19,ENTRIES!$G$2:$G$2000,"OUT") -> 0 | D19: =SUMIFS(ENTRIES!$E$2:$E$2000,ENTRIES!$O$2:$O$2000,A19,ENTRIES!$G$2:$G$2000,"OUT_FIXED") -> 0 | E19: =(SUMIFS(ENTRIES!$E$2:$E$2000,ENTRIES!$O$2:$O$2000,A19,ENTRIES!$G$2:$G$2000,"OUT_ASIA")+SUMIFS(ENTRIES!$E$2:$E$2000,ENTRIES!$O$2:$O$2000,A19,ENTRIES!$G$2:$G$2000,"OUT_ASIA_FLIGHTS")+SUMIFS(ENTRIES!$E$2:$E$2000,ENTRIES!$O$2:$O$2000,A19,ENTRIES!$G$2:$G$2000,"OUT_ASIA_INSURANCE")+SUMIFS(ENTRIES!$E$2:$E$2000,ENTRIES!$O$2:$O$2000,A19,ENTRIES!$G$2:$G$2000,"OUT_ASIA_PREPAID")) -> 0 | F19: =SUM(C19:E19) -> 0 | G19: =SUMIFS(ENTRIES!$E$2:$E$2000,ENTRIES!$O$2:$O$2000,A19,ENTRIES!$G$2:$G$2000,"TRANSFER") -> 0
A20: 2025-11 | B20: =SUMIFS(ENTRIES!$E$2:$E$2000,ENTRIES!$O$2:$O$2000,A20,ENTRIES!$G$2:$G$2000,"IN") -> 0 | C20: =SUMIFS(ENTRIES!$E$2:$E$2000,ENTRIES!$O$2:$O$2000,A20,ENTRIES!$G$2:$G$2000,"OUT") -> -18.9 | D20: =SUMIFS(ENTRIES!$E$2:$E$2000,ENTRIES!$O$2:$O$2000,A20,ENTRIES!$G$2:$G$2000,"OUT_FIXED") -> -112.77 | E20: =(SUMIFS(ENTRIES!$E$2:$E$2000,ENTRIES!$O$2:$O$2000,A20,ENTRIES!$G$2:$G$2000,"OUT_ASIA")+SUMIFS(ENTRIES!$E$2:$E$2000,ENTRIES!$O$2:$O$2000,A20,ENTRIES!$G$2:$G$2000,"OUT_ASIA_FLIGHTS")+SUMIFS(ENTRIES!$E$2:$E$2000,ENTRIES!$O$2:$O$2000,A20,ENTRIES!$G$2:$G$2000,"OUT_ASIA_INSURANCE")+SUMIFS(ENTRIES!$E$2:$E$2000,ENTRIES!$O$2:$O$2000,A20,ENTRIES!$G$2:$G$2000,"OUT_ASIA_PREPAID")) -> -1258.41 | F20: =SUM(C20:E20) -> -1390.08 | G20: =SUMIFS(ENTRIES!$E$2:$E$2000,ENTRIES!$O$2:$O$2000,A20,ENTRIES!$G$2:$G$2000,"TRANSFER") -> 0
A21: 2025-12 | B21: =SUMIFS(ENTRIES!$E$2:$E$2000,ENTRIES!$O$2:$O$2000,A21,ENTRIES!$G$2:$G$2000,"IN") -> 0 | C21: =SUMIFS(ENTRIES!$E$2:$E$2000,ENTRIES!$O$2:$O$2000,A21,ENTRIES!$G$2:$G$2000,"OUT") -> -0.45 | D21: =SUMIFS(ENTRIES!$E$2:$E$2000,ENTRIES!$O$2:$O$2000,A21,ENTRIES!$G$2:$G$2000,"OUT_FIXED") -> -112.77 | E21: =(SUMIFS(ENTRIES!$E$2:$E$2000,ENTRIES!$O$2:$O$2000,A21,ENTRIES!$G$2:$G$2000,"OUT_ASIA")+SUMIFS(ENTRIES!$E$2:$E$2000,ENTRIES!$O$2:$O$2000,A21,ENTRIES!$G$2:$G$2000,"OUT_ASIA_FLIGHTS")+SUMIFS(ENTRIES!$E$2:$E$2000,ENTRIES!$O$2:$O$2000,A21,ENTRIES!$G$2:$G$2000,"OUT_ASIA_INSURANCE")+SUMIFS(ENTRIES!$E$2:$E$2000,ENTRIES!$O$2:$O$2000,A21,ENTRIES!$G$2:$G$2000,"OUT_ASIA_PREPAID")) -> -381.69 | F21: =SUM(C21:E21) -> -494.91 | G21: =SUMIFS(ENTRIES!$E$2:$E$2000,ENTRIES!$O$2:$O$2000,A21,ENTRIES!$G$2:$G$2000,"TRANSFER") -> 0
A22: 2026-01 | B22: =SUMIFS(ENTRIES!$E$2:$E$2000,ENTRIES!$O$2:$O$2000,A22,ENTRIES!$G$2:$G$2000,"IN") -> 148.2 | C22: =SUMIFS(ENTRIES!$E$2:$E$2000,ENTRIES!$O$2:$O$2000,A22,ENTRIES!$G$2:$G$2000,"OUT") -> 0 | D22: =SUMIFS(ENTRIES!$E$2:$E$2000,ENTRIES!$O$2:$O$2000,A22,ENTRIES!$G$2:$G$2000,"OUT_FIXED") -> -112.77 | E22: =(SUMIFS(ENTRIES!$E$2:$E$2000,ENTRIES!$O$2:$O$2000,A22,ENTRIES!$G$2:$G$2000,"OUT_ASIA")+SUMIFS(ENTRIES!$E$2:$E$2000,ENTRIES!$O$2:$O$2000,A22,ENTRIES!$G$2:$G$2000,"OUT_ASIA_FLIGHTS")+SUMIFS(ENTRIES!$E$2:$E$2000,ENTRIES!$O$2:$O$2000,A22,ENTRIES!$G$2:$G$2000,"OUT_ASIA_INSURANCE")+SUMIFS(ENTRIES!$E$2:$E$2000,ENTRIES!$O$2:$O$2000,A22,ENTRIES!$G$2:$G$2000,"OUT_ASIA_PREPAID")) -> -461.51 | F22: =SUM(C22:E22) -> -574.28 | G22: =SUMIFS(ENTRIES!$E$2:$E$2000,ENTRIES!$O$2:$O$2000,A22,ENTRIES!$G$2:$G$2000,"TRANSFER") -> -500
A23: 2026-02 | B23: =SUMIFS(ENTRIES!$E$2:$E$2000,ENTRIES!$O$2:$O$2000,A23,ENTRIES!$G$2:$G$2000,"IN") -> 0 | C23: =SUMIFS(ENTRIES!$E$2:$E$2000,ENTRIES!$O$2:$O$2000,A23,ENTRIES!$G$2:$G$2000,"OUT") -> 0 | D23: =SUMIFS(ENTRIES!$E$2:$E$2000,ENTRIES!$O$2:$O$2000,A23,ENTRIES!$G$2:$G$2000,"OUT_FIXED") -> -208.77 | E23: =(SUMIFS(ENTRIES!$E$2:$E$2000,ENTRIES!$O$2:$O$2000,A23,ENTRIES!$G$2:$G$2000,"OUT_ASIA")+SUMIFS(ENTRIES!$E$2:$E$2000,ENTRIES!$O$2:$O$2000,A23,ENTRIES!$G$2:$G$2000,"OUT_ASIA_FLIGHTS")+SUMIFS(ENTRIES!$E$2:$E$2000,ENTRIES!$O$2:$O$2000,A23,ENTRIES!$G$2:$G$2000,"OUT_ASIA_INSURANCE")+SUMIFS(ENTRIES!$E$2:$E$2000,ENTRIES!$O$2:$O$2000,A23,ENTRIES!$G$2:$G$2000,"OUT_ASIA_PREPAID")) -> -353.28 | F23: =SUM(C23:E23) -> -562.05 | G23: =SUMIFS(ENTRIES!$E$2:$E$2000,ENTRIES!$O$2:$O$2000,A23,ENTRIES!$G$2:$G$2000,"TRANSFER") -> 500
A24: 2026-03 | B24: =SUMIFS(ENTRIES!$E$2:$E$2000,ENTRIES!$O$2:$O$2000,A24,ENTRIES!$G$2:$G$2000,"IN") -> 412 | C24: =SUMIFS(ENTRIES!$E$2:$E$2000,ENTRIES!$O$2:$O$2000,A24,ENTRIES!$G$2:$G$2000,"OUT") -> 0 | D24: =SUMIFS(ENTRIES!$E$2:$E$2000,ENTRIES!$O$2:$O$2000,A24,ENTRIES!$G$2:$G$2000,"OUT_FIXED") -> -112.77 | E24: =(SUMIFS(ENTRIES!$E$2:$E$2000,ENTRIES!$O$2:$O$2000,A24,ENTRIES!$G$2:$G$2000,"OUT_ASIA")+SUMIFS(ENTRIES!$E$2:$E$2000,ENTRIES!$O$2:$O$2000,A24,ENTRIES!$G$2:$G$2000,"OUT_ASIA_FLIGHTS")+SUMIFS(ENTRIES!$E$2:$E$2000,ENTRIES!$O$2:$O$2000,A24,ENTRIES!$G$2:$G$2000,"OUT_ASIA_INSURANCE")+SUMIFS(ENTRIES!$E$2:$E$2000,ENTRIES!$O$2:$O$2000,A24,ENTRIES!$G$2:$G$2000,"OUT_ASIA_PREPAID")) -> -404.6 | F24: =SUM(C24:E24) -> -517.37 | G24: =SUMIFS(ENTRIES!$E$2:$E$2000,ENTRIES!$O$2:$O$2000,A24,ENTRIES!$G$2:$G$2000,"TRANSFER") -> 0
A25: 2026-04 | B25: =SUMIFS(ENTRIES!$E$2:$E$2000,ENTRIES!$O$2:$O$2000,A25,ENTRIES!$G$2:$G$2000,"IN") -> 1487.1 | C25: =SUMIFS(ENTRIES!$E$2:$E$2000,ENTRIES!$O$2:$O$2000,A25,ENTRIES!$G$2:$G$2000,"OUT") -> -136.49 | D25: =SUMIFS(ENTRIES!$E$2:$E$2000,ENTRIES!$O$2:$O$2000,A25,ENTRIES!$G$2:$G$2000,"OUT_FIXED") -> -112.77 | E25: =(SUMIFS(ENTRIES!$E$2:$E$2000,ENTRIES!$O$2:$O$2000,A25,ENTRIES!$G$2:$G$2000,"OUT_ASIA")+SUMIFS(ENTRIES!$E$2:$E$2000,ENTRIES!$O$2:$O$2000,A25,ENTRIES!$G$2:$G$2000,"OUT_ASIA_FLIGHTS")+SUMIFS(ENTRIES!$E$2:$E$2000,ENTRIES!$O$2:$O$2000,A25,ENTRIES!$G$2:$G$2000,"OUT_ASIA_INSURANCE")+SUMIFS(ENTRIES!$E$2:$E$2000,ENTRIES!$O$2:$O$2000,A25,ENTRIES!$G$2:$G$2000,"OUT_ASIA_PREPAID")) -> -195.1 | F25: =SUM(C25:E25) -> -444.36 | G25: =SUMIFS(ENTRIES!$E$2:$E$2000,ENTRIES!$O$2:$O$2000,A25,ENTRIES!$G$2:$G$2000,"TRANSFER") -> 0
A26: 2026-05 | B26: =SUMIFS(ENTRIES!$E$2:$E$2000,ENTRIES!$O$2:$O$2000,A26,ENTRIES!$G$2:$G$2000,"IN") -> 2150 | C26: =SUMIFS(ENTRIES!$E$2:$E$2000,ENTRIES!$O$2:$O$2000,A26,ENTRIES!$G$2:$G$2000,"OUT") -> -636.69 | D26: =SUMIFS(ENTRIES!$E$2:$E$2000,ENTRIES!$O$2:$O$2000,A26,ENTRIES!$G$2:$G$2000,"OUT_FIXED") -> -100.27 | E26: =(SUMIFS(ENTRIES!$E$2:$E$2000,ENTRIES!$O$2:$O$2000,A26,ENTRIES!$G$2:$G$2000,"OUT_ASIA")+SUMIFS(ENTRIES!$E$2:$E$2000,ENTRIES!$O$2:$O$2000,A26,ENTRIES!$G$2:$G$2000,"OUT_ASIA_FLIGHTS")+SUMIFS(ENTRIES!$E$2:$E$2000,ENTRIES!$O$2:$O$2000,A26,ENTRIES!$G$2:$G$2000,"OUT_ASIA_INSURANCE")+SUMIFS(ENTRIES!$E$2:$E$2000,ENTRIES!$O$2:$O$2000,A26,ENTRIES!$G$2:$G$2000,"OUT_ASIA_PREPAID")) -> -220 | F26: =SUM(C26:E26) -> -956.96 | G26: =SUMIFS(ENTRIES!$E$2:$E$2000,ENTRIES!$O$2:$O$2000,A26,ENTRIES!$G$2:$G$2000,"TRANSFER") -> 0
A27: 2026-06 | B27: =SUMIFS(ENTRIES!$E$2:$E$2000,ENTRIES!$O$2:$O$2000,A27,ENTRIES!$G$2:$G$2000,"IN") -> 2210 | C27: =SUMIFS(ENTRIES!$E$2:$E$2000,ENTRIES!$O$2:$O$2000,A27,ENTRIES!$G$2:$G$2000,"OUT") -> -266.72 | D27: =SUMIFS(ENTRIES!$E$2:$E$2000,ENTRIES!$O$2:$O$2000,A27,ENTRIES!$G$2:$G$2000,"OUT_FIXED") -> -112.77 | E27: =(SUMIFS(ENTRIES!$E$2:$E$2000,ENTRIES!$O$2:$O$2000,A27,ENTRIES!$G$2:$G$2000,"OUT_ASIA")+SUMIFS(ENTRIES!$E$2:$E$2000,ENTRIES!$O$2:$O$2000,A27,ENTRIES!$G$2:$G$2000,"OUT_ASIA_FLIGHTS")+SUMIFS(ENTRIES!$E$2:$E$2000,ENTRIES!$O$2:$O$2000,A27,ENTRIES!$G$2:$G$2000,"OUT_ASIA_INSURANCE")+SUMIFS(ENTRIES!$E$2:$E$2000,ENTRIES!$O$2:$O$2000,A27,ENTRIES!$G$2:$G$2000,"OUT_ASIA_PREPAID")) -> 0 | F27: =SUM(C27:E27) -> -379.49 | G27: =SUMIFS(ENTRIES!$E$2:$E$2000,ENTRIES!$O$2:$O$2000,A27,ENTRIES!$G$2:$G$2000,"TRANSFER") -> 0
A28: Total | B28: =SUM(B19:B27) -> 6407.3 | C28: =SUM(C19:C27) -> -1059.25 | D28: =SUM(D19:D27) -> -985.66 | E28: =SUM(E19:E27) -> -3274.59 | F28: =SUM(F19:F27) -> -5319.5 | G28: =SUM(G19:G27) -> 0

Sheet CODES
A1: Code lists
A2: These lists feed the dropdowns on ENTRIES. Add a code here before using it there.
A4: type | B4: meaning | D4: group | F4: source | G4: kind | H4: what it is | J4: daily_code | K4: meaning
A5: IN | B5: Income: earned or received for keeps | D5: SALARY | F5: BANK_CURRENT | G5: real | H5: Current account | J5: bf | K5: Breakfast
A6: OUT | B6: Spending, Netherlands and Europe | D6: TAX_REFUNDS | F6: BANK_SAVINGS | G6: real | H6: Savings account | J6: l | K6: Lunch
A7: OUT_FIXED | B7: Fixed costs, all year | D7: INTEREST | F7: BANK_PENSION | G7: real | H7: Pension savings, locked until retirement | J7: d | K7: Dinner
A8: OUT_ASIA | B8: Daily life in Asia | D8: MISC_IN | F8: CREDIT_CARD | G8: real | H8: Credit card | J8: c | K8: Coffee
A9: OUT_ASIA_FLIGHTS | B9: Flights to and from Asia | D9: GROCERIES | F9: FOREIGN_BANK | G9: real | H9: Small account abroad | J9: s | K9: Snacks and drinks
A10: OUT_ASIA_INSURANCE | B10: Travel insurance | D10: EATING_OUT | F10: MULTI_EUR | G10: real | H10: Multi-currency app, EUR pocket | J10: alc | K10: Alcohol
A11: OUT_ASIA_PREPAID | B11: Visa, vaccinations, paid before leaving | D11: MISC | F11: MULTI_THB | G11: real | H11: Multi-currency app, THB pocket | J11: h | K11: Housing
A12: TRANSFER | B12: Money moving between my own sources; must net to zero | D12: CLOTHING_CARE | F12: BANK_ONLINE | G12: real | H12: Online bank / money-transfer service | J12: scoot | K12: Scooter
A13: OPENING_BALANCE | B13: Opening balance or zero-amount checkpoint | D13: TRAVEL_NL | F13: ONLINE_WALLET | G13: real | H13: Online payment wallet | J13: taxi | K13: Taxi or ride-hailing
A14: PAPER_GAIN_LOSS | B14: Revaluation, e.g. crypto | D14: TRAVEL_EUROPE | F14: CASH_EUR | G14: real | H14: Cash, euro | J14: tix | K14: Bus, train, ferry
A15: UNCATEGORISED | B15: Imported, not yet labelled | D15: FIXED_COSTS | F15: CASH_THB | G15: real | H15: Cash, Thai baht | J15: yoga | K15: Classes
D16: ASIA_DAILY | F16: CASH_VND | G16: real | H16: Cash, Vietnamese dong | J16: lndry | K16: Laundry
D17: ASIA_MISC | F17: CASH_USD | G17: real | H17: Cash, US dollar | J17: tour | K17: Sights
D18: ASIA_FLIGHTS | F18: CASH_AED | G18: real | H18: Cash, UAE dirham | J18: tip | K18: Tips
D19: ASIA_PREP | F19: CRYPTO | G19: real | H19: Crypto holding | J19: visa | K19: Visa extension
D20: PREPAID_UNUSED | F20: RECEIVABLES | G20: helper | H20: Owed to me by an organisation | J20: misc | K20: Everything else
D21: TRANSFER | F21: PAYABLES | G21: helper | H21: I owe someone | J21: diff | K21: Cash count difference
D22: OPENING_BALANCE | F22: PREPAID | G22: helper | H22: Services paid ahead | J22: in | K22: Cash coming in
D23: PAPER_GAIN_LOSS | F23: DEPOSITS | G23: helper | H23: Deposits held by landlords and rentals
F24: INSURER_POT | G24: helper | H24: Deductible instalments with insurer
F25: PERSON_A | G25: helper | H25: Loans to and from one friend
F26: TAB_FRIEND_B | G26: helper | H26: Cash with a friend who pays by QR
F27: FX_DIFF | G27: helper | H27: Rounding differences on repayments
F28: RECLASS | G28: helper | H28: Moves between categories
F29: SUSPENSE | G29: helper | H29: Money not yet placed
F30: STATS_ONLY | G30: helper | H30: Zero-amount rows with local details

Sheet WHEREABOUTS
A1: Location | B1: Country | C1: Work | D1: Arrival | E1: days
A2: Hometown | B2: NL | C2: =FALSE() -> FALSE | D2: 45931 | E2: =D3-D2 -> 34
A3: Dubai airport | B3: AE | C3: =FALSE() -> FALSE | D3: 45965 | E3: =D4-D3 -> 1
A4: Chiang Mai | B4: TH | C4: =FALSE() -> FALSE | D4: 45966 | E4: =D5-D4 -> 26
A5: Koh Phangan | B5: TH | C5: =FALSE() -> FALSE | D5: 45992 | E5: =D6-D5 -> 31
A6: Hoi An | B6: VN | C6: =FALSE() -> FALSE | D6: 46023 | E6: =D7-D6 -> 109
A7: Hometown | B7: NL | C7: =FALSE() -> FALSE | D7: 46132 | E7: =D8-D7 -> 11
A8: Campsite job | B8: NL | C8: =TRUE() -> TRUE | D8: 46143
A10: One row per arrival. A stay lasts until the day before the next arrival; the last one runs to the end of the ledger. Country is the two-letter code; every country outside Europe counts as a stay in Asia. Work is TRUE for a stay where I had a job.
